Workbook

Sheet Comparison
A1: Year | B1: ICAP primary market | C1: Secondary market | D1: EEX primary market | G1: EU ETS Zertifikatspreise: Primär- vs. Sekundärmarkt | H1: EU ETS allowance price comparison (annual averages) | I1: EU ETS allowance price comparison (annual averages) | J1: EU ETS allowance price comparison (annual averages) | K1: EU ETS allowance price comparison (annual averages)
A2: 2019 | B2: {=AVERAGE(_xlfn._xlws.FILTER('ETS price ICAP'!$E$3:$E$5000,YEAR('ETS price ICAP'!$A$3:$A$5000)=$A2))} -> 24.723125 | C2: {=AVERAGE(_xlfn._xlws.FILTER('ETS price ICAP'!$F$3:$F$5000,YEAR('ETS price ICAP'!$A$3:$A$5000)=$A2))} -> 24.889412 | D2: {=AVERAGE(_xlfn._xlws.FILTER('ETS price EEX 2019 Spot Primary'!$E$5:$E$220,YEAR('ETS price EEX 2019 Spot Primary'!$A$5:$A$220)=$A2))} -> 24.72338
A3: 2020 | B3: {=AVERAGE(_xlfn._xlws.FILTER('ETS price ICAP'!$E$3:$E$5000,YEAR('ETS price ICAP'!$A$3:$A$5000)=$A3))} -> 24.386603 | C3: {=AVERAGE(_xlfn._xlws.FILTER('ETS price ICAP'!$F$3:$F$5000,YEAR('ETS price ICAP'!$A$3:$A$5000)=$A3))} -> 24.544 | G3: Year | H3: ICAP Primärmarkt | I3: ICAP Sekundärmarkt | J3: EEX Primärmarkt | K3: EEX Sekundärmarkt
A4: =A3+1 -> 2021 | B4: {=AVERAGE(_xlfn._xlws.FILTER('ETS price ICAP'!$E$3:$E$5000,YEAR('ETS price ICAP'!$A$3:$A$5000)=$A4))} -> 54.15157 | C4: {=AVERAGE(_xlfn._xlws.FILTER('ETS price ICAP'!$F$3:$F$5000,YEAR('ETS price ICAP'!$A$3:$A$5000)=$A4))} -> 53.135686 | G4: 2013 | H4: 4.3731 | I4: null | J4: 4.3793 | K4: zum Verkauf
A5: =A4+1 -> 2022 | B5: {=AVERAGE(_xlfn._xlws.FILTER('ETS price ICAP'!$E$3:$E$5000,YEAR('ETS price ICAP'!$A$3:$A$5000)=$A5))} -> 80.184045 | C5: {=AVERAGE(_xlfn._xlws.FILTER('ETS price ICAP'!$F$3:$F$5000,YEAR('ETS price ICAP'!$A$3:$A$5000)=$A5))} -> 81.073462 | D5: {=AVERAGE(_xlfn._xlws.FILTER('ETS price EEX 2022 Spot Primary'!$F$6:$F$250,YEAR('ETS price EEX 2022 Spot Primary'!$A$6:$A$250)=$A5))} -> 80.184045 | G5: 2014 | H5: 5.9123 | I5: null | J5: 5.9123 | K5: zum Verkauf
A6: =A5+1 -> 2023 | B6: {=AVERAGE(_xlfn._xlws.FILTER('ETS price ICAP'!$E$3:$E$5000,YEAR('ETS price ICAP'!$A$3:$A$5000)=$A6))} -> 83.596502 | C6: {=AVERAGE(_xlfn._xlws.FILTER('ETS price ICAP'!$F$3:$F$5000,YEAR('ETS price ICAP'!$A$3:$A$5000)=$A6))} -> 85.384 | G6: 2015 | H6: 7.619 | I6: null | J6: 7.6103 | K6: zum Verkauf
A7: =A6+1 -> 2024 | B7: {=AVERAGE(_xlfn._xlws.FILTER('ETS price ICAP'!$E$3:$E$5000,YEAR('ETS price ICAP'!$A$3:$A$5000)=$A7))} -> 64.757014 | C7: {=AVERAGE(_xlfn._xlws.FILTER('ETS price ICAP'!$F$3:$F$5000,YEAR('ETS price ICAP'!$A$3:$A$5000)=$A7))} -> 66.586538 | G7: 2016 | H7: 5.2475 | I7: null | J7: 5.2475 | K7: zum Verkauf
A8: =A7+1 -> 2025 | B8: {=AVERAGE(_xlfn._xlws.FILTER('ETS price ICAP'!$E$3:$E$5000,YEAR('ETS price ICAP'!$A$3:$A$5000)=$A8))} -> 73.452488 | C8: {=AVERAGE(_xlfn._xlws.FILTER('ETS price ICAP'!$F$3:$F$5000,YEAR('ETS price ICAP'!$A$3:$A$5000)=$A8))} -> 72.686154 | G8: 2017 | H8: 5.7573 | I8: null | J8: 5.7953 | K8: zum Verkauf
A9: =A8+1 -> 2026 | B9: {=AVERAGE(_xlfn._xlws.FILTER('ETS price ICAP'!$E$3:$E$5000,YEAR('ETS price ICAP'!$A$3:$A$5000)=$A9))} -> 74.928636 | C9: {=AVERAGE(_xlfn._xlws.FILTER('ETS price ICAP'!$F$3:$F$5000,YEAR('ETS price ICAP'!$A$3:$A$5000)=$A9))} -> #DIV/0! | G9: 2018 | H9: 15.4771 | I9: null | J9: 15.5615 | K9: zum Verkauf
G10: 2019 | H10: 24.7231 | I10: 24.8894 | J10: 24.7234 | K10: zum Verkauf
G11: 2020 | H11: 24.3866 | I11: 24.544 | J11: 24.37 | K11: zum Verkauf
G12: 2021 | H12: 54.1516 | I12: 53.1357 | J12: 54.1276 | K12: zum Verkauf
G13: 2022 | H13: 80.184 | I13: 81.0735 | J13: 80.184 | K13: zum Verkauf
G14: 2023 | H14: 83.5965 | I14: 85.384 | J14: 83.5965 | K14: zum Verkauf
G15: 2024 | H15: 64.757 | I15: 66.5865 | J15: 64.757 | K15: zum Verkauf
G16: 2025 | H16: 73.4525 | I16: 72.6862 | J16: 73.4525 | K16: zum Verkauf
G17: 2026 | H17: 74.9286 | I17: null | J17: null | K17: zum Verkauf

Sheet ETS price ICAP
B1: European Union Emissions Trading System (from 2019, download)
A2: Date | B2: Exchange rate EUR/EUR | C2: Exchange rate EUR/USD | D2: Market Currency | E2: Primary Market | F2: Secondary Market
A3: 43472 | B3: 1 | C3: 1.1416409 | D3: EUR | E3: 23.01 | F3: 22.39
A4: 43473 | B4: 1 | C4: 1.1416409 | D4: EUR | E4: 22.4
A5: 43475 | B5: 1 | C5: 1.1416409 | D5: EUR | E5: 21.4
A6: 43479 | B6: 1 | C6: 1.1416409 | D6: EUR | E6: 21.95 | F6: 23.42
A7: 43480 | B7: 1 | C7: 1.1416409 | D7: EUR | E7: 22.55
A8: 43481 | B8: 1 | C8: 1.1416409 | D8: EUR | E8: 22.81
A9: 43482 | B9: 1 | C9: 1.1416409 | D9: EUR | E9: 23.55
A10: 43486 | B10: 1 | C10: 1.1416409 | D10: EUR | E10: 24.22 | F10: 24.48
A11: 43487 | B11: 1 | C11: 1.1416409 | D11: EUR | E11: 24.42
A12: 43489 | B12: 1 | C12: 1.1416409 | D12: EUR | E12: 24.6
A13: 43493 | B13: 1 | C13: 1.1416409 | D13: EUR | E13: 23.01 | F13: 22.7
A14: 43494 | B14: 1 | C14: 1.1416409 | D14: EUR | E14: 22.43
A15: 43495 | B15: 1 | C15: 1.1416409 | D15: EUR | E15: 22.91
A16: 43496 | B16: 1 | C16: 1.1416409 | D16: EUR | E16: 22.3
A17: 43497 | B17: 1 | C17: 1.135115 | D17: EUR | E17: 21.38
A18: 43500 | B18: 1 | C18: 1.135115 | D18: EUR | E18: 21.38 | F18: 23.16
A19: 43501 | B19: 1 | C19: 1.135115 | D19: EUR | E19: 22.93
A20: 43503 | B20: 1 | C20: 1.135115 | D20: EUR | E20: 23.8
A21: 43504 | B21: 1 | C21: 1.135115 | D21: EUR | E21: 23.28
A22: 43507 | B22: 1 | C22: 1.135115 | D22: EUR | E22: 21.8 | F22: 20.85
A23: 43508 | B23: 1 | C23: 1.135115 | D23: EUR | E23: 21.71
A24: 43509 | B24: 1 | C24: 1.135115 | D24: EUR | E24: 20.01
A25: 43510 | B25: 1 | C25: 1.135115 | D25: EUR | E25: 20.86
A26: 43511 | B26: 1 | C26: 1.135115 | D26: EUR | E26: 19.99
A27: 43514 | B27: 1 | C27: 1.135115 | D27: EUR | E27: 20.14 | F27: 19.69
A28: 43515 | B28: 1 | C28: 1.135115 | D28: EUR | E28: 20.26
A29: 43517 | B29: 1 | C29: 1.135115 | D29: EUR | E29: 19.85
A30: 43518 | B30: 1 | C30: 1.135115 | D30: EUR | E30: 18.35
A31: 43521 | B31: 1 | C31: 1.135115 | D31: EUR | E31: 18.62 | F31: 20.83
A32: 43522 | B32: 1 | C32: 1.135115 | D32: EUR | E32: 19.6
A33: 43523 | B33: 1 | C33: 1.135115 | D33: EUR | E33: 20.31
A34: 43524 | B34: 1 | C34: 1.135115 | D34: EUR | E34: 20.9
A35: 43525 | B35: 1 | C35: 1.1302476 | D35: EUR | E35: 21.31
A36: 43528 | B36: 1 | C36: 1.1302476 | D36: EUR | E36: 22.12 | F36: 22.9
A37: 43529 | B37: 1 | C37: 1.1302476 | D37: EUR | E37: 22.86
A38: 43531 | B38: 1 | C38: 1.1302476 | D38: EUR | E38: 22.03
A39: 43532 | B39: 1 | C39: 1.1302476 | D39: EUR | E39: 22.88
A40: 43535 | B40: 1 | C40: 1.1302476 | D40: EUR | E40: 22.6 | F40: 22.42
A41: 43536 | B41: 1 | C41: 1.1302476 | D41: EUR | E41: 22.48
A42: 43537 | B42: 1 | C42: 1.1302476 | D42: EUR | E42: 21.98
A43: 43538 | B43: 1 | C43: 1.1302476 | D43: EUR | E43: 22.23
A44: 43539 | B44: 1 | C44: 1.1302476 | D44: EUR | E44: 22.77
A45: 43542 | B45: 1 | C45: 1.1302476 | D45: EUR | E45: 21.5 | F45: 21.24
A46: 43543 | B46: 1 | C46: 1.1302476 | D46: EUR | E46: 21.35
A47: 43545 | B47: 1 | C47: 1.1302476 | D47: EUR | E47: 21.1
A48: 43546 | B48: 1 | C48: 1.1302476 | D48: EUR | E48: 20.64
A49: 43549 | B49: 1 | C49: 1.1302476 | D49: EUR | E49: 20.6 | F49: 21.63
A50: 43550 | B50: 1 | C50: 1.1302476 | D50: EUR | E50: 21.17
A51: 43551 | B51: 1 | C51: 1.1302476 | D51: EUR | E51: 21.45
A52: 43552 | B52: 1 | C52: 1.1302476 | D52: EUR | E52: 21.55
A53: 43553 | B53: 1 | C53: 1.1302476 | D53: EUR | E53: 21.83
A54: 43556 | B54: 1 | C54: 1.123825 | D54: EUR | E54: 21.06 | F54: 23.22
A55: 43557 | B55: 1 | C55: 1.123825 | D55: EUR | E55: 21.4
A56: 43559 | B56: 1 | C56: 1.123825 | D56: EUR | E56: 23.65
A57: 43560 | B57: 1 | C57: 1.123825 | D57: EUR | E57: 24.17
A58: 43563 | B58: 1 | C58: 1.123825 | D58: EUR | E58: 24.07 | F58: 25.97
A59: 43564 | B59: 1 | C59: 1.123825 | D59: EUR | E59: 25.2
A60: 43565 | B60: 1 | C60: 1.123825 | D60: EUR | E60: 26.21
A61: 43566 | B61: 1 | C61: 1.123825 | D61: EUR | E61: 25.88
A62: 43567 | B62: 1 | C62: 1.123825 | D62: EUR | E62: 26.72
A63: 43570 | B63: 1 | C63: 1.123825 | D63: EUR | E63: 27 | F63: 27.04
A64: 43571 | B64: 1 | C64: 1.123825 | D64: EUR | E64: 26.8
A65: 43573 | B65: 1 | C65: 1.123825 | D65: EUR | E65: 26.92
A66: 43577 | B66: 1 | C66: 1.123825 | D66: EUR | F66: 26.99
A67: 43578 | B67: 1 | C67: 1.123825 | D67: EUR | E67: 27.17
A68: 43579 | B68: 1 | C68: 1.123825 | D68: EUR | E68: 27.02
A69: 43580 | B69: 1 | C69: 1.123825 | D69: EUR | E69: 27.46
A70: 43581 | B70: 1 | C70: 1.123825 | D70: EUR | E70: 26.79
A71: 43584 | B71: 1 | C71: 1.123825 | D71: EUR | E71: 25.81 | F71: 25.67
A72: 43585 | B72: 1 | C72: 1.123825 | D72: EUR | E72: 25.85
A73: 43587 | B73: 1 | C73: 1.1184591 | D73: EUR | E73: 25.04
A74: 43588 | B74: 1 | C74: 1.1184591 | D74: EUR | E74: 24.32
A75: 43591 | B75: 1 | C75: 1.1184591 | D75: EUR | F75: 26.15
A76: 43592 | B76: 1 | C76: 1.1184591 | D76: EUR | E76: 25.65
A77: 43593 | B77: 1 | C77: 1.1184591 | D77: EUR | E77: 26.5
A78: 43594 | B78: 1 | C78: 1.1184591 | D78: EUR | E78: 26.81
A79: 43595 | B79: 1 | C79: 1.1184591 | D79: EUR | E79: 26.35
A80: 43598 | B80: 1 | C80: 1.1184591 | D80: EUR | E80: 25.25 | F80: 25.49
A81: 43599 | B81: 1 | C81: 1.1184591 | D81: EUR | E81: 25.03
A82: 43601 | B82: 1 | C82: 1.1184591 | D82: EUR | E82: 25.81
A83: 43602 | B83: 1 | C83: 1.1184591 | D83: EUR | E83: 25.01
A84: 43605 | B84: 1 | C84: 1.1184591 | D84: EUR | E84: 24.91 | F84: 25.7
A85: 43606 | B85: 1 | C85: 1.1184591 | D85: EUR | E85: 25.01
A86: 43607 | B86: 1 | C86: 1.1184591 | D86: EUR | E86: 25.65
A87: 43608 | B87: 1 | C87: 1.1184591 | D87: EUR | E87: 26.05
A88: 43609 | B88: 1 | C88: 1.1184591 | D88: EUR | E88: 25.61
A89: 43612 | B89: 1 | C89: 1.1184591 | D89: EUR | F89: 25.27
A90: 43613 | B90: 1 | C90: 1.1184591 | D90: EUR | E90: 25.3
A91: 43619 | B91: 1 | C91: 1.12934 | D91: EUR | E91: 23.96 | F91: 24.21
A92: 43620 | B92: 1 | C92: 1.12934 | D92: EUR | E92: 23.86
A93: 43621 | B93: 1 | C93: 1.12934 | D93: EUR | E93: 24.42
A94: 43622 | B94: 1 | C94: 1.12934 | D94: EUR | E94: 24.07
A95: 43623 | B95: 1 | C95: 1.12934 | D95: EUR | E95: 24.24
A96: 43626 | B96: 1 | C96: 1.12934 | D96: EUR | F96: 25
A97: 43627 | B97: 1 | C97: 1.12934 | D97: EUR | E97: 25.12
A98: 43629 | B98: 1 | C98: 1.12934 | D98: EUR | E98: 24.92
A99: 43630 | B99: 1 | C99: 1.12934 | D99: EUR | E99: 24.67
A100: 43633 | B100: 1 | C100: 1.12934 | D100: EUR | E100: 24.78 | F100: 25.1
...

Sheet ETS price EEX 2019 Spot Primary
A1: More information
J2: EEX Emissions market / Primary Market Auction
A3: References | E3: Prices | J3: Volumes | U3: Participants | W3: Revenue | Y3: Revenue
A4: Date | B4: Time | C4: Auction Name | D4: Contract | E4: Auction Price €/tCO2 | F4: Minimum Bid €/tCO2 | G4: Maximum Bid €/tCO2 | H4: Mean €/tCO2 | I4: Median €/tCO2 | J4: Auction Volume tCO2 | K4: Total Amount of Bids | L4: Number of bids submitted | M4: Number of successful bids | N4: Average number of bids per bidder | O4: Average bid size | P4: Average volume bid per bidder | Q4: Standard deviation of bid volume per bidder | R4: Average volume won per bidder | S4: Standard deviation of volume won per bidder | T4: Cover Ratio | U4: Total Number of Bidders | V4: Number of Successful Bidders | W4: Total Revenue € | X4: Country | Y4: Austria (AT) | Z4: Belgium (BE) | AA4: Bulgaria (BG) | AB4: Cyprus (CY) | AC4: Czech Republic (CZ) | AD4: Germany (DE) | AE4: Denmark (DK) | AF4: Estonia (EE) | AG4: Greece (EL) | AH4: Spain (ES) | AI4: Finland (FI) | AJ4: France (FR) | AK4: Croatia (HR) | AL4: Hungary (HU) | AM4: Ireland (IE) | AN4: Iceland (IS) | AO4: Italy (IT) | AP4: Liechtenstein (LI) | AQ4: Lithuania (LT) | AR4: Luxembourg (LU) | AS4: Latvia (LV) | AT4: Malta (MT) | AU4: Netherlands (NL) | AV4: Norway (NO) | AW4: Poland (PL) | AX4: Portugal (PT) | AY4: Romania (RO) | AZ4: Sweden (SE) | BA4: Slovenia (SI) | BB4: Slovakia (SK) | BC4: Innovation Fund
A5: 43815 | B5: 43815.459 | C5: Auction 3. Period CAP2-EU | D5: T3PA | E5: 24.21 | F5: 21 | G5: 26 | H5: 24.09 | I5: 24.05 | J5: 3013000 | K5: 5333000 | L5: 92 | M5: 19 | N5: 4.6 | O5: 57967 | P5: 266650 | Q5: 391858 | R5: 273909 | S5: 289081 | T5: 1.77 | U5: 20 | V5: 11 | W5: 72944730 | X5: EU | Y5: 1658385 | Z5: 2590470 | AA5: 3716235 | AB5: 387360 | AC5: 4866210 | AE5: 1319445 | AF5: 1416285 | AG5: 4188330 | AH5: 9163485 | AI5: 1973115 | AJ5: 5616720 | AK5: 883665 | AL5: 1718910 | AM5: 1392075 | AN5: 508410 | AO5: 9357165 | AP5: 0 | AQ5: 798930 | AR5: 169470 | AS5: 484200 | AT5: 133155 | AU5: 3280455 | AV5: 5761980 | AX5: 2336265 | AY5: 5519880 | AZ5: 1125765 | BA5: 714195 | BB5: 1864170
A6: 43812 | B6: 43812.459 | C6: Auction 3. Period DE | D6: T3PA | E6: 25.33 | F6: 24.76 | G6: 30 | H6: 25.34 | I6: 25.28 | J6: 2840000 | K6: 4827000 | L6: 83 | M6: 27 | N6: 4.37 | O6: 58157 | P6: 254053 | Q6: 331093 | R6: 202857 | S6: 276386 | T6: 1.7 | U6: 19 | V6: 14 | W6: 71937200 | X6: DE | AD6: 71937200
A7: 43811 | B7: 43811.459 | C7: Auction 3. Period CAP2-EU | D7: T3PA | E7: 24.62 | F7: 21 | G7: 26 | H7: 24.48 | I7: 24.42 | J7: 2744000 | K7: 6226500 | L7: 97 | M7: 18 | N7: 4.41 | O7: 64191 | P7: 283023 | Q7: 413993 | R7: 274400 | S7: 240189 | T7: 2.27 | U7: 22 | V7: 10 | W7: 67557280 | X7: EU | Y7: 1354100 | Z7: 2634340 | AA7: 3249840 | AB7: 184650 | AC7: 4653180 | AE7: 1231000 | AF7: 1070970 | AG7: 3717620 | AH7: 9072470 | AI7: 1612610 | AJ7: 5268680 | AK7: 529330 | AL7: 1686470 | AM7: 898630 | AN7: 283130 | AO7: 9454080 | AP7: 0 | AQ7: 615500 | AR7: 123100 | AS7: 307750 | AT7: 123100 | AU7: 3225220 | AV7: 5601050 | AX7: 1883430 | AY7: 5539500 | AZ7: 935560 | BA7: 492400 | BB7: 1809570
A8: 43809 | B8: 43809.459 | C8: Auction 3. Period CAP2-EU | D8: T3PA | E8: 24.98 | F8: 23.99 | G8: 27 | H8: 25.08 | I8: 24.96 | J8: 2744000 | K8: 5103000 | L8: 102 | M8: 43 | N8: 4.25 | O8: 50029 | P8: 212625 | Q8: 401348 | R8: 137200 | S8: 253407 | T8: 1.86 | U8: 24 | V8: 20 | W8: 68545120 | X8: EU | Y8: 1373900 | Z8: 2672860 | AA8: 3297360 | AB8: 187350 | AC8: 4721220 | AE8: 1249000 | AF8: 1086630 | AG8: 3771980 | AH8: 9205130 | AI8: 1636190 | AJ8: 5345720 | AK8: 537070 | AL8: 1711130 | AM8: 911770 | AN8: 287270 | AO8: 9592320 | AP8: 0 | AQ8: 624500 | AR8: 124900 | AS8: 312250 | AT8: 124900 | AU8: 3272380 | AV8: 5682950 | AX8: 1910970 | AY8: 5620500 | AZ8: 949240 | BA8: 499600 | BB8: 1836030
A9: 43808 | B9: 43808.459 | C9: Auction 3. Period CAP2-EU | D9: T3PA | E9: 24.4 | F9: 21 | G9: 26 | H9: 24.3 | I9: 24.37 | J9: 2744000 | K9: 5004000 | L9: 72 | M9: 31 | N9: 4.24 | O9: 69500 | P9: 294353 | Q9: 489700 | R9: 182933 | S9: 270365 | T9: 1.82 | U9: 17 | V9: 15 | W9: 66953600 | X9: EU | Y9: 1342000 | Z9: 2610800 | AA9: 3220800 | AB9: 183000 | AC9: 4611600 | AE9: 1220000 | AF9: 1061400 | AG9: 3684400 | AH9: 8991400 | AI9: 1598200 | AJ9: 5221600 | AK9: 524600 | AL9: 1671400 | AM9: 890600 | AN9: 280600 | AO9: 9369600 | AP9: 0 | AQ9: 610000 | AR9: 122000 | AS9: 305000 | AT9: 122000 | AU9: 3196400 | AV9: 5551000 | AX9: 1866600 | AY9: 5490000 | AZ9: 927200 | BA9: 488000 | BB9: 1793400
A10: 43805 | B10: 43805.459 | C10: Auction 3. Period DE | D10: T3PA | E10: 24.7 | F10: 21 | G10: 26 | H10: 24.62 | I10: 24.66 | J10: 2834500 | K10: 4825000 | L10: 84 | M10: 27 | N10: 4.2 | O10: 57440 | P10: 241250 | Q10: 322738 | R10: 188967 | S10: 203612 | T10: 1.7 | U10: 20 | V10: 15 | W10: 70012150 | X10: DE | AD10: 70012150
A11: 43804 | B11: 43804.459 | C11: Auction 3. Period CAP2-EU | D11: T3PA | E11: 24.5 | F11: 21 | G11: 26 | H11: 24.47 | I11: 24.43 | J11: 2744000 | K11: 5354000 | L11: 92 | M11: 29 | N11: 4.38 | O11: 58196 | P11: 254952 | Q11: 396446 | R11: 182933 | S11: 230405 | T11: 1.95 | U11: 21 | V11: 15 | W11: 67228000 | X11: EU | Y11: 1347500 | Z11: 2621500 | AA11: 3234000 | AB11: 183750 | AC11: 4630500 | AE11: 1225000 | AF11: 1065750 | AG11: 3699500 | AH11: 9028250 | AI11: 1604750 | AJ11: 5243000 | AK11: 526750 | AL11: 1678250 | AM11: 894250 | AN11: 281750 | AO11: 9408000 | AP11: 0 | AQ11: 612500 | AR11: 122500 | AS11: 306250 | AT11: 122500 | AU11: 3209500 | AV11: 5573750 | AX11: 1874250 | AY11: 5512500 | AZ11: 931000 | BA11: 490000 | BB11: 1800750
A12: 43803 | B12: 43803.459 | C12: Auction 3. Period CAP2-PL | D12: T3PA | E12: 24.1 | F12: 21 | G12: 26 | H12: 23.98 | I12: 23.93 | J12: 4717500 | K12: 9654000 | L12: 102 | M12: 23 | N12: 5.1 | O12: 94647 | P12: 482700 | Q12: 711585 | R12: 524167 | S12: 495642 | T12: 2.05 | U12: 20 | V12: 9 | W12: 113691750 | X12: PL | AW12: 113691750
A13: 43802 | B13: 43802.459 | C13: Auction 3. Period CAP2-EU | D13: T3PA | E13: 24.41 | F13: 21 | G13: 30.01 | H13: 24.5 | I13: 24.37 | J13: 2744000 | K13: 4858000 | L13: 92 | M13: 32 | N13: 3.83 | O13: 52804 | P13: 202417 | Q13: 295921 | R13: 137200 | S13: 191560 | T13: 1.77 | U13: 24 | V13: 20 | W13: 66981040 | X13: EU | Y13: 1342550 | Z13: 2611870 | AA13: 3222120 | AB13: 183075 | AC13: 4613490 | AE13: 1220500 | AF13: 1061835 | AG13: 3685910 | AH13: 8995085 | AI13: 1598855 | AJ13: 5223740 | AK13: 524815 | AL13: 1672085 | AM13: 890965 | AN13: 280715 | AO13: 9373440 | AP13: 0 | AQ13: 610250 | AR13: 122050 | AS13: 305125 | AT13: 122050 | AU13: 3197710 | AV13: 5553275 | AX13: 1867365 | AY13: 5492250 | AZ13: 927580 | BA13: 488200 | BB13: 1794135
A14: 43801 | B14: 43801.459 | C14: Auction 3. Period CAP2-EU | D14: T3PA | E14: 24.62 | F14: 21 | G14: 27 | H14: 24.63 | I14: 24.62 | J14: 2744000 | K14: 4298500 | L14: 95 | M14: 43 | N14: 3.96 | O14: 45247 | P14: 179104 | Q14: 301607 | R14: 144421 | S14: 259953 | T14: 1.57 | U14: 24 | V14: 19 | W14: 67557280 | X14: EU | Y14: 1354100 | Z14: 2634340 | AA14: 3249840 | AB14: 184650 | AC14: 4653180 | AE14: 1231000 | AF14: 1070970 | AG14: 3717620 | AH14: 9072470 | AI14: 1612610 | AJ14: 5268680 | AK14: 529330 | AL14: 1686470 | AM14: 898630 | AN14: 283130 | AO14: 9454080 | AP14: 0 | AQ14: 615500 | AR14: 123100 | AS14: 307750 | AT14: 123100 | AU14: 3225220 | AV14: 5601050 | AX14: 1883430 | AY14: 5539500 | AZ14: 935560 | BA14: 492400 | BB14: 1809570
A15: 43798 | B15: 43798.459 | C15: Auction 3. Period DE | D15: T3PA | E15: 25.03 | F15: 21 | G15: 30 | H15: 24.94 | I15: 24.95 | J15: 2834500 | K15: 4833500 | L15: 75 | M15: 17 | N15: 3.75 | O15: 64447 | P15: 241675 | Q15: 363959 | R15: 257682 | S15: 365284 | T15: 1.71 | U15: 20 | V15: 11 | W15: 70947535 | X15: DE | AD15: 70947535
A16: 43797 | B16: 43797.459 | C16: Auction 3. Period CAP2-EU | D16: T3PA | E16: 24.91 | F16: 21 | G16: 30 | H16: 24.96 | I16: 24.95 | J16: 2744000 | K16: 3432000 | L16: 66 | M16: 47 | N16: 3.67 | O16: 52000 | P16: 190667 | Q16: 267948 | R16: 161412 | S16: 218847 | T16: 1.25 | U16: 18 | V16: 17 | W16: 68353040 | X16: EU | Y16: 1370050 | Z16: 2665370 | AA16: 3288120 | AB16: 186825 | AC16: 4707990 | AE16: 1245500 | AF16: 1083585 | AG16: 3761410 | AH16: 9179335 | AI16: 1631605 | AJ16: 5330740 | AK16: 535565 | AL16: 1706335 | AM16: 909215 | AN16: 286465 | AO16: 9565440 | AP16: 0 | AQ16: 622750 | AR16: 124550 | AS16: 311375 | AT16: 124550 | AU16: 3263210 | AV16: 5667025 | AX16: 1905615 | AY16: 5604750 | AZ16: 946580 | BA16: 498200 | BB16: 1830885
A17: 43795 | B17: 43795.459 | C17: Auction 3. Period CAP2-EU | D17: T3PA | E17: 24.29 | F17: 21 | G17: 28 | H17: 24.44 | I17: 24.28 | J17: 2744000 | K17: 4322000 | L17: 70 | M17: 33 | N17: 3.89 | O17: 61743 | P17: 240111 | Q17: 394392 | R17: 171500 | S17: 260578 | T17: 1.58 | U17: 18 | V17: 16 | W17: 66651760 | X17: EU | Y17: 1335950 | Z17: 2599030 | AA17: 3206280 | AB17: 182175 | AC17: 4590810 | AE17: 1214500 | AF17: 1056615 | AG17: 3667790 | AH17: 8950865 | AI17: 1590995 | AJ17: 5198060 | AK17: 522235 | AL17: 1663865 | AM17: 886585 | AN17: 279335 | AO17: 9327360 | AP17: 0 | AQ17: 607250 | AR17: 121450 | AS17: 303625 | AT17: 121450 | AU17: 3181990 | AV17: 5525975 | AX17: 1858185 | AY17: 5465250 | AZ17: 923020 | BA17: 485800 | BB17: 1785315
A18: 43794 | B18: 43794.459 | C18: Auction 3. Period CAP2-EU | D18: T3PA | E18: 24.52 | F18: 21 | G18: 29 | H18: 24.72 | I18: 24.49 | J18: 2744000 | K18: 4337500 | L18: 86 | M18: 32 | N18: 4.1 | O18: 50436 | P18: 206548 | Q18: 364494 | R18: 211077 | S18: 304430 | T18: 1.58 | U18: 21 | V18: 13 | W18: 67282880 | X18: EU | Y18: 1348600 | Z18: 2623640 | AA18: 3236640 | AB18: 183900 | AC18: 4634280 | AE18: 1226000 | AF18: 1066620 | AG18: 3702520 | AH18: 9035620 | AI18: 1606060 | AJ18: 5247280 | AK18: 527180 | AL18: 1679620 | AM18: 894980 | AN18: 281980 | AO18: 9415680 | AP18: 0 | AQ18: 613000 | AR18: 122600 | AS18: 306500 | AT18: 122600 | AU18: 3212120 | AV18: 5578300 | AX18: 1875780 | AY18: 5517000 | AZ18: 931760 | BA18: 490400 | BB18: 1802220
A19: 43791 | B19: 43791.459 | C19: Auction 3. Period DE | D19: T3PA | E19: 24.32 | F19: 21 | G19: 30.01 | H19: 24.38 | I19: 24.29 | J19: 2834500 | K19: 4141500 | L19: 84 | M19: 31 | N19: 4.2 | O19: 49304 | P19: 207075 | Q19: 334700 | R19: 166735 | S19: 290548 | T19: 1.46 | U19: 20 | V19: 17 | W19: 68935040 | X19: DE | AD19: 68935040
A20: 43790 | B20: 43790.459 | C20: Auction 3. Period CAP2-EU | D20: T3PA | E20: 23.96 | F20: 21 | G20: 30 | H20: 23.99 | I20: 23.95 | J20: 2744000 | K20: 4156500 | L20: 93 | M20: 41 | N20: 4.04 | O20: 44694 | P20: 180717 | Q20: 226243 | R20: 137200 | S20: 175491 | T20: 1.51 | U20: 23 | V20: 20 | W20: 65746240 | X20: EU | Y20: 1317800 | Z20: 2563720 | AA20: 3162720 | AB20: 179700 | AC20: 4528440 | AE20: 1198000 | AF20: 1042260 | AG20: 3617960 | AH20: 8829260 | AI20: 1569380 | AJ20: 5127440 | AK20: 515140 | AL20: 1641260 | AM20: 874540 | AN20: 275540 | AO20: 9200640 | AP20: 0 | AQ20: 599000 | AR20: 119800 | AS20: 299500 | AT20: 119800 | AU20: 3138760 | AV20: 5450900 | AX20: 1832940 | AY20: 5391000 | AZ20: 910480 | BA20: 479200 | BB20: 1761060
A21: 43789 | B21: 43789.459 | C21: Auction 3. Period CAP2-PL | D21: T3PA | E21: 23.34 | F21: 21 | G21: 30 | H21: 23.32 | I21: 23.22 | J21: 4714500 | K21: 8406000 | L21: 106 | M21: 25 | N21: 5.05 | O21: 79302 | P21: 400286 | Q21: 475960 | R21: 362654 | S21: 325295 | T21: 1.78 | U21: 21 | V21: 13 | W21: 110036430 | X21: PL | AW21: 110036430
A22: 43788 | B22: 43788.459 | C22: Auction 3. Period CAP2-EU | D22: T3PA | E22: 23.62 | F22: 23.21 | G22: 30 | H22: 23.67 | I22: 23.45 | J22: 2744000 | K22: 5216000 | L22: 96 | M22: 15 | N22: 4.36 | O22: 54333 | P22: 237091 | Q22: 308603 | R22: 228667 | S22: 274099 | T22: 1.9 | U22: 22 | V22: 12 | W22: 64813280 | X22: EU | Y22: 1299100 | Z22: 2527340 | AA22: 3117840 | AB22: 177150 | AC22: 4464180 | AE22: 1181000 | AF22: 1027470 | AG22: 3566620 | AH22: 8703970 | AI22: 1547110 | AJ22: 5054680 | AK22: 507830 | AL22: 1617970 | AM22: 862130 | AN22: 271630 | AO22: 9070080 | AP22: 0 | AQ22: 590500 | AR22: 118100 | AS22: 295250 | AT22: 118100 | AU22: 3094220 | AV22: 5373550 | AX22: 1806930 | AY22: 5314500 | AZ22: 897560 | BA22: 472400 | BB22: 1736070
A23: 43787 | B23: 43787.459 | C23: Auction 3. Period CAP2-EU | D23: T3PA | E23: 23.41 | F23: 21 | G23: 28 | H23: 23.39 | I23: 23.32 | J23: 2744000 | K23: 5689000 | L23: 107 | M23: 29 | N23: 4.12 | O23: 53168 | P23: 218808 | Q23: 336040 | R23: 182933 | S23: 219753 | T23: 2.07 | U23: 26 | V23: 15 | W23: 64237040 | X23: EU | Y23: 1287550 | Z23: 2504870 | AA23: 3090120 | AB23: 175575 | AC23: 4424490 | AE23: 1170500 | AF23: 1018335 | AG23: 3534910 | AH23: 8626585 | AI23: 1533355 | AJ23: 5009740 | AK23: 503315 | AL23: 1603585 | AM23: 854465 | AN23: 269215 | AO23: 8989440 | AP23: 0 | AQ23: 585250 | AR23: 117050 | AS23: 292625 | AT23: 117050 | AU23: 3066710 | AV23: 5325775 | AX23: 1790865 | AY23: 5267250 | AZ23: 889580 | BA23: 468200 | BB23: 1720635
A24: 43784 | B24: 43784.459 | C24: Auction 3. Period DE | D24: T3PA | E24: 23.41 | F24: 21 | G24: 30 | H24: 23.51 | I24: 23.38 | J24: 2834500 | K24: 4691000 | L24: 101 | M24: 40 | N24: 4.59 | O24: 46446 | P24: 213227 | Q24: 217251 | R24: 166735 | S24: 187014 | T24: 1.65 | U24: 22 | V24: 17 | W24: 66355645 | X24: DE | AD24: 66355645
A25: 43783 | B25: 43783.459 | C25: Auction 3. Period CAP2-EU | D25: T3PA | E25: 24.28 | F25: 21 | G25: 30 | H25: 24.45 | I25: 24.22 | J25: 2744000 | K25: 5342500 | L25: 97 | M25: 33 | N25: 4.04 | O25: 55077 | P25: 222604 | Q25: 348420 | R25: 130667 | S25: 156295 | T25: 1.95 | U25: 24 | V25: 21 | W25: 66624320 | X25: EU | Y25: 1335400 | Z25: 2597960 | AA25: 3204960 | AB25: 182100 | AC25: 4588920 | AE25: 1214000 | AF25: 1056180 | AG25: 3666280 | AH25: 8947180 | AI25: 1590340 | AJ25: 5195920 | AK25: 522020 | AL25: 1663180 | AM25: 886220 | AN25: 279220 | AO25: 9323520 | AP25: 0 | AQ25: 607000 | AR25: 121400 | AS25: 303500 | AT25: 121400 | AU25: 3180680 | AV25: 5523700 | AX25: 1857420 | AY25: 5463000 | AZ25: 922640 | BA25: 485600 | BB25: 1784580
A26: 43781 | B26: 43781.459 | C26: Auction 3. Period CAP2-EU | D26: T3PA | E26: 24.95 | F26: 21 | G26: 30 | H26: 25.02 | I26: 24.9 | J26: 2744000 | K26: 4525000 | L26: 93 | M26: 33 | N26: 4.43 | O26: 48656 | P26: 215476 | Q26: 258397 | R26: 161412 | S26: 195897 | T26: 1.65 | U26: 21 | V26: 17 | W26: 68462800 | X26: EU | Y26: 1372250 | Z26: 2669650 | AA26: 3293400 | AB26: 187125 | AC26: 4715550 | AE26: 1247500 | AF26: 1085325 | AG26: 3767450 | AH26: 9194075 | AI26: 1634225 | AJ26: 5339300 | AK26: 536425 | AL26: 1709075 | AM26: 910675 | AN26: 286925 | AO26: 9580800 | AP26: 0 | AQ26: 623750 | AR26: 124750 | AS26: 311875 | AT26: 124750 | AU26: 3268450 | AV26: 5676125 | AX26: 1908675 | AY26: 5613750 | AZ26: 948100 | BA26: 499000 | BB26: 1833825
A27: 43780 | B27: 43780.459 | C27: Auction 3. Period CAP2-EU | D27: T3PA | E27: 25.21 | F27: 21 | G27: 29 | H27: 25.37 | I27: 25.17 | J27: 2744000 | K27: 4884500 | L27: 88 | M27: 28 | N27: 4 | O27: 55506 | P27: 222023 | Q27: 351515 | R27: 196000 | S27: 259584 | T27: 1.78 | U27: 22 | V27: 14 | W27: 69176240 | X27: EU | Y27: 1386550 | Z27: 2697470 | AA27: 3327720 | AB27: 189075 | AC27: 4764690 | AE27: 1260500 | AF27: 1096635 | AG27: 3806710 | AH27: 9289885 | AI27: 1651255 | AJ27: 5394940 | AK27: 542015 | AL27: 1726885 | AM27: 920165 | AN27: 289915 | AO27: 9680640 | AP27: 0 | AQ27: 630250 | AR27: 126050 | AS27: 315125 | AT27: 126050 | AU27: 3302510 | AV27: 5735275 | AX27: 1928565 | AY27: 5672250 | AZ27: 957980 | BA27: 504200 | BB27: 1852935
A28: 43777 | B28: 43777.459 | C28: Auction 3. Period DE | D28: T3PA | E28: 24.62 | F28: 20.51 | G28: 30.01 | H28: 24.42 | I28: 24.55 | J28: 2834500 | K28: 6297500 | L28: 102 | M28: 26 | N28: 4.86 | O28: 61740 | P28: 299881 | Q28: 366294 | R28: 202464 | S28: 238237 | T28: 2.22 | U28: 21 | V28: 14 | W28: 69785390 | X28: DE | AD28: 69785390
A29: 43776 | B29: 43776.459 | C29: Auction 3. Period CAP2-EU | D29: T3PA | E29: 24.86 | F29: 21 | G29: 29 | H29: 24.92 | I29: 24.84 | J29: 2744000 | K29: 5027500 | L29: 95 | M29: 40 | N29: 4.13 | O29: 52921 | P29: 218587 | Q29: 346633 | R29: 144421 | S29: 228020 | T29: 1.83 | U29: 23 | V29: 19 | W29: 68215840 | X29: EU | Y29: 1367300 | Z29: 2660020 | AA29: 3281520 | AB29: 186450 | AC29: 4698540 | AE29: 1243000 | AF29: 1081410 | AG29: 3753860 | AH29: 9160910 | AI29: 1628330 | AJ29: 5320040 | AK29: 534490 | AL29: 1702910 | AM29: 907390 | AN29: 285890 | AO29: 9546240 | AP29: 0 | AQ29: 621500 | AR29: 124300 | AS29: 310750 | AT29: 124300 | AU29: 3256660 | AV29: 5655650 | AX29: 1901790 | AY29: 5593500 | AZ29: 944680 | BA29: 497200 | BB29: 1827210
A30: 43775 | B30: 43775.625 | C30: EUAA Auction CAP2-EU | D30: EAA3 | E30: 25.18 | F30: 24.1 | G30: 25.45 | H30: 24.86 | I30: 25 | J30: 884500 | K30: 3202500 | L30: 75 | M30: 10 | N30: 7.5 | O30: 42700 | P30: 320250 | Q30: 290402 | R30: 176900 | S30: 93504 | T30: 3.62 | U30: 10 | V30: 5 | W30: 22271710 | X30: EU | Y30: 491010 | Z30: 528780 | AA30: 163670 | AB30: 289570 | AC30: 264390 | AE30: 541370 | AF30: 12590 | AG30: 1007200 | AH30: 3336350 | AI30: 453240 | AJ30: 2480230 | AK30: 113310 | AL30: 201440 | AM30: 415470 | AN30: 579140 | AO30: 2958650 | AP30: 0 | AQ30: 37770 | AR30: 25180 | AS30: 88130 | AT30: 138490 | AU30: 717630 | AV30: 5741040 | AX30: 566550 | AY30: 314750 | AZ30: 717630 | BA30: 37770 | BB30: 50360
A31: 43775 | B31: 43775.459 | C31: Auction 3. Period CAP2-PL | D31: T3PA | E31: 25.1 | F31: 21 | G31: 29 | H31: 25.08 | I31: 25.07 | J31: 4714500 | K31: 8190500 | L31: 114 | M31: 41 | N31: 4.56 | O31: 71846 | P31: 327620 | Q31: 451769 | R31: 224500 | S31: 347953 | T31: 1.74 | U31: 25 | V31: 21 | W31: 118333950 | X31: PL | AW31: 118333950
A32: 43774 | B32: 43774.459 | C32: Auction 3. Period CAP2-EU | D32: T3PA | E32: 25.8 | F32: 25.5 | G32: 30 | H32: 25.88 | I32: 25.75 | J32: 2744000 | K32: 4482500 | L32: 75 | M32: 25 | N32: 3.41 | O32: 59767 | P32: 203750 | Q32: 238236 | R32: 161412 | S32: 193036 | T32: 1.63 | U32: 22 | V32: 17 | W32: 70795200 | X32: EU | Y32: 1419000 | Z32: 2760600 | AA32: 3405600 | AB32: 193500 | AC32: 4876200 | AE32: 1290000 | AF32: 1122300 | AG32: 3895800 | AH32: 9507300 | AI32: 1689900 | AJ32: 5521200 | AK32: 554700 | AL32: 1767300 | AM32: 941700 | AN32: 296700 | AO32: 9907200 | AP32: 0 | AQ32: 645000 | AR32: 129000 | AS32: 322500 | AT32: 129000 | AU32: 3379800 | AV32: 5869500 | AX32: 1973700 | AY32: 5805000 | AZ32: 980400 | BA32: 516000 | BB32: 1896300
A33: 43773 | B33: 43773.459 | C33: Auction 3. Period CAP2-EU | D33: T3PA | E33: 24.93 | F33: 21 | G33: 30 | H33: 24.99 | I33: 24.91 | J33: 2744000 | K33: 4806500 | L33: 68 | M33: 30 | N33: 3.09 | O33: 70684 | P33: 218477 | Q33: 314265 | R33: 152444 | S33: 201695 | T33: 1.75 | U33: 22 | V33: 18 | W33: 68407920 | X33: EU | Y33: 1371150 | Z33: 2667510 | AA33: 3290760 | AB33: 186975 | AC33: 4711770 | AE33: 1246500 | AF33: 1084455 | AG33: 3764430 | AH33: 9186705 | AI33: 1632915 | AJ33: 5335020 | AK33: 535995 | AL33: 1707705 | AM33: 909945 | AN33: 286695 | AO33: 9573120 | AP33: 0 | AQ33: 623250 | AR33: 124650 | AS33: 311625 | AT33: 124650 | AU33: 3265830 | AV33: 5671575 | AX33: 1907145 | AY33: 5609250 | AZ33: 947340 | BA33: 498600 | BB33: 1832355
A34: 43770 | B34: 43770.459 | C34: Auction 3. Period DE | D34: T3PA | E34: 25.71 | F34: 25.22 | G34: 30 | H34: 25.8 | I34: 25.61 | J34: 2834500 | K34: 5144000 | L34: 50 | M34: 15 | N34: 3.85 | O34: 102880 | P34: 395692 | Q34: 359214 | R34: 314944 | S34: 257829 | T34: 1.81 | U34: 13 | V34: 9 | W34: 72874995 | X34: DE | AD34: 72874995
A35: 43769 | B35: 43769.459 | C35: Auction 3. Period CAP2-EU | D35: T3PA | E35: 25.95 | F35: 25.6 | G35: 30 | H35: 26.2 | I35: 25.95 | J35: 2744000 | K35: 4333500 | L35: 61 | M35: 31 | N35: 3.39 | O35: 71041 | P35: 240750 | Q35: 326802 | R35: 182933 | S35: 232824 | T35: 1.58 | U35: 18 | V35: 15 | W35: 71206800 | X35: EU | Y35: 1427250 | Z35: 2776650 | AA35: 3425400 | AB35: 194625 | AC35: 4904550 | AE35: 1297500 | AF35: 1128825 | AG35: 3918450 | AH35: 9562575 | AI35: 1699725 | AJ35: 5553300 | AK35: 557925 | AL35: 1777575 | AM35: 947175 | AN35: 298425 | AO35: 9964800 | AP35: 0 | AQ35: 648750 | AR35: 129750 | AS35: 324375 | AT35: 129750 | AU35: 3399450 | AV35: 5903625 | AX35: 1985175 | AY35: 5838750 | AZ35: 986100 | BA35: 519000 | BB35: 1907325
A36: 43767 | B36: 43767.459 | C36: Auction 3. Period CAP2-EU | D36: T3PA | E36: 25.4 | F36: 21 | G36: 30 | H36: 25.37 | I36: 25.21 | J36: 2744000 | K36: 5253500 | L36: 95 | M36: 16 | N36: 3.96 | O36: 55300 | P36: 218896 | Q36: 292925 | R36: 228667 | S36: 254794 | T36: 1.91 | U36: 24 | V36: 12 | W36: 69697600 | X36: EU | Y36: 1397000 | Z36: 2717800 | AA36: 3352800 | AB36: 190500 | AC36: 4800600 | AE36: 1270000 | AF36: 1104900 | AG36: 3835400 | AH36: 9359900 | AI36: 1663700 | AJ36: 5435600 | AK36: 546100 | AL36: 1739900 | AM36: 927100 | AN36: 292100 | AO36: 9753600 | AP36: 0 | AQ36: 635000 | AR36: 127000 | AS36: 317500 | AT36: 127000 | AU36: 3327400 | AV36: 5778500 | AX36: 1943100 | AY36: 5715000 | AZ36: 965200 | BA36: 508000 | BB36: 1866900
A37: 43766 | B37: 43766.459 | C37: Auction 3. Period CAP2-EU | D37: T3PA | E37: 24.68 | F37: 21 | G37: 29 | H37: 24.78 | I37: 24.61 | J37: 2744000 | K37: 4270500 | L37: 94 | M37: 31 | N37: 4.09 | O37: 45431 | P37: 185674 | Q37: 286559 | R37: 171500 | S37: 281456 | T37: 1.56 | U37: 23 | V37: 16 | W37: 67721920 | X37: EU | Y37: 1357400 | Z37: 2640760 | AA37: 3257760 | AB37: 185100 | AC37: 4664520 | AE37: 1234000 | AF37: 1073580 | AG37: 3726680 | AH37: 9094580 | AI37: 1616540 | AJ37: 5281520 | AK37: 530620 | AL37: 1690580 | AM37: 900820 | AN37: 283820 | AO37: 9477120 | AP37: 0 | AQ37: 617000 | AR37: 123400 | AS37: 308500 | AT37: 123400 | AU37: 3233080 | AV37: 5614700 | AX37: 1888020 | AY37: 5553000 | AZ37: 937840 | BA37: 493600 | BB37: 1813980
A38: 43763 | B38: 43763.459 | C38: Auction 3. Period DE | D38: T3PA | E38: 24.86 | F38: 21 | G38: 29 | H38: 24.98 | I38: 24.91 | J38: 2834500 | K38: 4146000 | L38: 73 | M38: 48 | N38: 4.06 | O38: 56795 | P38: 230333 | Q38: 277507 | R38: 166735 | S38: 182748 | T38: 1.46 | U38: 18 | V38: 17 | W38: 70465670 | X38: DE | AD38: 70465670
A39: 43762 | B39: 43762.459 | C39: Auction 3. Period CAP2-EU | D39: T3PA | E39: 24.61 | F39: 21 | G39: 28 | H39: 24.59 | I39: 24.55 | J39: 2744500 | K39: 4239500 | L39: 87 | M39: 35 | N39: 3.78 | O39: 48730 | P39: 184326 | Q39: 226056 | R39: 144447 | S39: 194613 | T39: 1.54 | U39: 23 | V39: 19 | W39: 67542145 | X39: EU | Y39: 1353550 | Z39: 2633270 | AA39: 3248520 | AB39: 184575 | AC39: 4651290 | AE39: 1230500 | AF39: 1070535 | AG39: 3716110 | AH39: 9068785 | AI39: 1611955 | AJ39: 5266540 | AK39: 529115 | AL39: 1685785 | AM39: 898265 | AN39: 283015 | AO39: 9450240 | AP39: 12305 | AQ39: 615250 | AR39: 123050 | AS39: 307625 | AT39: 123050 | AU39: 3223910 | AV39: 5598775 | AX39: 1882665 | AY39: 5537250 | AZ39: 935180 | BA39: 492200 | BB39: 1808835
A40: 43761 | B40: 43761.459 | C40: Auction 3. Period CAP2-PL | D40: T3PA | E40: 25.09 | F40: 21 | G40: 35 | H40: 25.15 | I40: 25.01 | J40: 4714500 | K40: 7667000 | L40: 116 | M40: 34 | N40: 5.04 | O40: 66095 | P40: 333348 | Q40: 536107 | R40: 277324 | S40: 387581 | T40: 1.63 | U40: 23 | V40: 17 | W40: 118286805 | X40: PL | AW40: 118286805
A41: 43760 | B41: 43760.459 | C41: Auction 3. Period CAP2-EU | D41: T3PA | E41: 25.7 | F41: 21 | G41: 29 | H41: 25.55 | I41: 25.57 | J41: 2744500 | K41: 6301500 | L41: 92 | M41: 13 | N41: 4 | O41: 68495 | P41: 273978 | Q41: 395013 | R41: 249500 | S41: 314618 | T41: 2.3 | U41: 23 | V41: 11 | W41: 70533650 | X41: EU | Y41: 1413500 | Z41: 2749900 | AA41: 3392400 | AB41: 192750 | AC41: 4857300 | AE41: 1285000 | AF41: 1117950 | AG41: 3880700 | AH41: 9470450 | AI41: 1683350 | AJ41: 5499800 | AK41: 552550 | AL41: 1760450 | AM41: 938050 | AN41: 295550 | AO41: 9868800 | AP41: 12850 | AQ41: 642500 | AR41: 128500 | AS41: 321250 | AT41: 128500 | AU41: 3366700 | AV41: 5846750 | AX41: 1966050 | AY41: 5782500 | AZ41: 976600 | BA41: 514000 | BB41: 1888950
A42: 43759 | B42: 43759.459 | C42: Auction 3. Period CAP2-EU | D42: T3PA | E42: 25.9 | F42: 0.01 | G42: 29 | H42: 25.53 | I42: 25.92 | J42: 2744500 | K42: 3878500 | L42: 71 | M42: 40 | N42: 3.38 | O42: 54627 | P42: 184690 | Q42: 260453 | R42: 144447 | S42: 207902 | T42: 1.41 | U42: 21 | V42: 19 | W42: 71082550 | X42: EU | Y42: 1424500 | Z42: 2771300 | AA42: 3418800 | AB42: 194250 | AC42: 4895100 | AE42: 1295000 | AF42: 1126650 | AG42: 3910900 | AH42: 9544150 | AI42: 1696450 | AJ42: 5542600 | AK42: 556850 | AL42: 1774150 | AM42: 945350 | AN42: 297850 | AO42: 9945600 | AP42: 12950 | AQ42: 647500 | AR42: 129500 | AS42: 323750 | AT42: 129500 | AU42: 3392900 | AV42: 5892250 | AX42: 1981350 | AY42: 5827500 | AZ42: 984200 | BA42: 518000 | BB42: 1903650
A43: 43756 | B43: 43756.459 | C43: Auction 3. Period DE | D43: T3PA | E43: 25.64 | F43: 21 | G43: 29 | H43: 25.64 | I43: 25.66 | J43: 2834500 | K43: 4343000 | L43: 70 | M43: 41 | N43: 3.89 | O43: 62043 | P43: 241278 | Q43: 325368 | R43: 188967 | S43: 258879 | T43: 1.53 | U43: 18 | V43: 15 | W43: 72676580 | X43: DE | AD43: 72676580
A44: 43755 | B44: 43755.459 | C44: Auction 3. Period CAP2-EU | D44: T3PA | E44: 25.96 | F44: 21 | G44: 40 | H44: 26.01 | I44: 25.75 | J44: 2744500 | K44: 6533000 | L44: 84 | M44: 17 | N44: 3.65 | O44: 77774 | P44: 284043 | Q44: 405719 | R44: 211115 | S44: 271262 | T44: 2.38 | U44: 23 | V44: 13 | W44: 71247220 | X44: EU | Y44: 1427800 | Z44: 2777720 | AA44: 3426720 | AB44: 194700 | AC44: 4906440 | AE44: 1298000 | AF44: 1129260 | AG44: 3919960 | AH44: 9566260 | AI44: 1700380 | AJ44: 5555440 | AK44: 558140 | AL44: 1778260 | AM44: 947540 | AN44: 298540 | AO44: 9968640 | AP44: 12980 | AQ44: 649000 | AR44: 129800 | AS44: 324500 | AT44: 129800 | AU44: 3400760 | AV44: 5905900 | AX44: 1985940 | AY44: 5841000 | AZ44: 986480 | BA44: 519200 | BB44: 1908060
A45: 43753 | B45: 43753.459 | C45: Auction 3. Period CAP2-EU | D45: T3PA | E45: 24.48 | F45: 21 | G45: 26 | H45: 24.44 | I45: 24.45 | J45: 2744500 | K45: 4501000 | L45: 78 | M45: 28 | N45: 3.55 | O45: 57705 | P45: 204591 | Q45: 246047 | R45: 182967 | S45: 202825 | T45: 1.64 | U45: 22 | V45: 15 | W45: 67185360 | X45: EU | Y45: 1346400 | Z45: 2619360 | AA45: 3231360 | AB45: 183600 | AC45: 4626720 | AE45: 1224000 | AF45: 1064880 | AG45: 3696480 | AH45: 9020880 | AI45: 1603440 | AJ45: 5238720 | AK45: 526320 | AL45: 1676880 | AM45: 893520 | AN45: 281520 | AO45: 9400320 | AP45: 12240 | AQ45: 612000 | AR45: 122400 | AS45: 306000 | AT45: 122400 | AU45: 3206880 | AV45: 5569200 | AX45: 1872720 | AY45: 5508000 | AZ45: 930240 | BA45: 489600 | BB45: 1799280
A46: 43752 | B46: 43752.459 | C46: Auction 3. Period CAP2-EU | D46: T3PA | E46: 23.82 | F46: 21 | G46: 26 | H46: 23.78 | I46: 23.75 | J46: 2744500 | K46: 4946500 | L46: 83 | M46: 24 | N46: 3.32 | O46: 59596 | P46: 197860 | Q46: 320049 | R46: 171531 | S46: 210865 | T46: 1.8 | U46: 25 | V46: 16 | W46: 65373990 | X46: EU | Y46: 1310100 | Z46: 2548740 | AA46: 3144240 | AB46: 178650 | AC46: 4501980 | AE46: 1191000 | AF46: 1036170 | AG46: 3596820 | AH46: 8777670 | AI46: 1560210 | AJ46: 5097480 | AK46: 512130 | AL46: 1631670 | AM46: 869430 | AN46: 273930 | AO46: 9146880 | AP46: 11910 | AQ46: 595500 | AR46: 119100 | AS46: 297750 | AT46: 119100 | AU46: 3120420 | AV46: 5419050 | AX46: 1822230 | AY46: 5359500 | AZ46: 905160 | BA46: 476400 | BB46: 1750770
A47: 43749 | B47: 43749.459 | C47: Auction 3. Period DE | D47: T3PA | E47: 23.62 | F47: 21 | G47: 29 | H47: 23.62 | I47: 23.59 | J47: 2834500 | K47: 4516500 | L47: 86 | M47: 36 | N47: 3.91 | O47: 52517 | P47: 205295 | Q47: 346690 | R47: 166735 | S47: 261997 | T47: 1.59 | U47: 22 | V47: 17 | W47: 66950890 | X47: DE | AD47: 66950890
A48: 43748 | B48: 43748.459 | C48: Auction 3. Period CAP2-EU | D48: T3PA | E48: 22.83 | F48: 21 | G48: 25 | H48: 22.8 | I48: 22.71 | J48: 2744500 | K48: 5672000 | L48: 104 | M48: 24 | N48: 3.71 | O48: 54538 | P48: 202571 | Q48: 284464 | R48: 152472 | S48: 198401 | T48: 2.07 | U48: 28 | V48: 18 | W48: 62656935 | X48: EU | Y48: 1255650 | Z48: 2442810 | AA48: 3013560 | AB48: 171225 | AC48: 4314870 | AE48: 1141500 | AF48: 993105 | AG48: 3447330 | AH48: 8412855 | AI48: 1495365 | AJ48: 4885620 | AK48: 490845 | AL48: 1563855 | AM48: 833295 | AN48: 262545 | AO48: 8766720 | AP48: 11415 | AQ48: 570750 | AR48: 114150 | AS48: 285375 | AT48: 114150 | AU48: 2990730 | AV48: 5193825 | AX48: 1746495 | AY48: 5136750 | AZ48: 867540 | BA48: 456600 | BB48: 1678005
A49: 43747 | B49: 43747.625 | C49: EUAA Auction DE | D49: EAA3 | E49: 22.32 | F49: 21.97 | G49: 23.05 | H49: 22.22 | I49: 22.2 | J49: 801500 | K49: 2377000 | L49: 49 | M49: 10 | N49: 5.44 | O49: 48510 | P49: 264111 | Q49: 211315 | R49: 160300 | S49: 109732 | T49: 2.97 | U49: 9 | V49: 5 | W49: 17889480 | X49: DE | AD49: 17889480
A50: 43747 | B50: 43747.459 | C50: Auction 3. Period CAP2-PL | D50: T3PA | E50: 22.16 | F50: 21 | G50: 25 | H50: 22.09 | I50: 22 | J50: 4714500 | K50: 8219000 | L50: 99 | M50: 23 | N50: 4.3 | O50: 83020 | P50: 357348 | Q50: 504935 | R50: 362654 | S50: 398066 | T50: 1.74 | U50: 23 | V50: 13 | W50: 104473320 | X50: PL | AW50: 104473320
A51: 43746 | B51: 43746.459 | C51: Auction 3. Period CAP2-EU | D51: T3PA | E51: 23.37 | F51: 22.92 | G51: 26 | H51: 23.35 | I51: 23.24 | J51: 2744500 | K51: 5633500 | L51: 100 | M51: 25 | N51: 4 | O51: 56335 | P51: 225340 | Q51: 252492 | R51: 161441 | S51: 208232 | T51: 2.05 | U51: 25 | V51: 17 | W51: 64138965 | X51: EU | Y51: 1285350 | Z51: 2500590 | AA51: 3084840 | AB51: 175275 | AC51: 4416930 | AE51: 1168500 | AF51: 1016595 | AG51: 3528870 | AH51: 8611845 | AI51: 1530735 | AJ51: 5001180 | AK51: 502455 | AL51: 1600845 | AM51: 853005 | AN51: 268755 | AO51: 8974080 | AP51: 11685 | AQ51: 584250 | AR51: 116850 | AS51: 292125 | AT51: 116850 | AU51: 3061470 | AV51: 5316675 | AX51: 1787805 | AY51: 5258250 | AZ51: 888060 | BA51: 467400 | BB51: 1717695
A52: 43745 | B52: 43745.459 | C52: Auction 3. Period CAP2-EU | D52: T3PA | E52: 22.77 | F52: 22.32 | G52: 32 | H52: 22.99 | I52: 22.75 | J52: 2744500 | K52: 4780000 | L52: 94 | M52: 37 | N52: 3.92 | O52: 50851 | P52: 199167 | Q52: 262237 | R52: 152472 | S52: 212537 | T52: 1.74 | U52: 24 | V52: 18 | W52: 62492265 | X52: EU | Y52: 1252350 | Z52: 2436390 | AA52: 3005640 | AB52: 170775 | AC52: 4303530 | AE52: 1138500 | AF52: 990495 | AG52: 3438270 | AH52: 8390745 | AI52: 1491435 | AJ52: 4872780 | AK52: 489555 | AL52: 1559745 | AM52: 831105 | AN52: 261855 | AO52: 8743680 | AP52: 11385 | AQ52: 569250 | AR52: 113850 | AS52: 284625 | AT52: 113850 | AU52: 2982870 | AV52: 5180175 | AX52: 1741905 | AY52: 5123250 | AZ52: 865260 | BA52: 455400 | BB52: 1673595
A53: 43742 | B53: 43742.459 | C53: Auction 3. Period DE | D53: T3PA | E53: 23.41 | F53: 22.99 | G53: 29 | H53: 23.48 | I53: 23.37 | J53: 2834500 | K53: 4171500 | L53: 83 | M53: 29 | N53: 4.37 | O53: 50259 | P53: 219553 | Q53: 333100 | R53: 188967 | S53: 294746 | T53: 1.47 | U53: 19 | V53: 15 | W53: 66355645 | X53: DE | AD53: 66355645
A54: 43741 | B54: 43741.459 | C54: Auction 3. Period CAP2-EU | D54: T3PA | E54: 24.03 | F54: 23.46 | G54: 26 | H54: 23.95 | I54: 23.81 | J54: 2744500 | K54: 6749500 | L54: 71 | M54: 18 | N54: 3.38 | O54: 95063 | P54: 321405 | Q54: 681110 | R54: 228708 | S54: 391416 | T54: 2.46 | U54: 21 | V54: 12 | W54: 65950335 | X54: EU | Y54: 1321650 | Z54: 2571210 | AA54: 3171960 | AB54: 180225 | AC54: 4541670 | AE54: 1201500 | AF54: 1045305 | AG54: 3628530 | AH54: 8855055 | AI54: 1573965 | AJ54: 5142420 | AK54: 516645 | AL54: 1646055 | AM54: 877095 | AN54: 276345 | AO54: 9227520 | AP54: 12015 | AQ54: 600750 | AR54: 120150 | AS54: 300375 | AT54: 120150 | AU54: 3147930 | AV54: 5466825 | AX54: 1838295 | AY54: 5406750 | AZ54: 913140 | BA54: 480600 | BB54: 1766205
A55: 43739 | B55: 43739.459 | C55: Auction 3. Period CAP2-EU | D55: T3PA | E55: 24.4 | F55: 23.99 | G55: 27.5 | H55: 24.52 | I55: 24.42 | J55: 2744500 | K55: 3986000 | L55: 90 | M55: 50 | N55: 3.46 | O55: 44289 | P55: 153308 | Q55: 243364 | R55: 137225 | S55: 251782 | T55: 1.45 | U55: 26 | V55: 20 | W55: 66965800 | X55: EU | Y55: 1342000 | Z55: 2610800 | AA55: 3220800 | AB55: 183000 | AC55: 4611600 | AE55: 1220000 | AF55: 1061400 | AG55: 3684400 | AH55: 8991400 | AI55: 1598200 | AJ55: 5221600 | AK55: 524600 | AL55: 1671400 | AM55: 890600 | AN55: 280600 | AO55: 9369600 | AP55: 12200 | AQ55: 610000 | AR55: 122000 | AS55: 305000 | AT55: 122000 | AU55: 3196400 | AV55: 5551000 | AX55: 1866600 | AY55: 5490000 | AZ55: 927200 | BA55: 488000 | BB55: 1793400
A56: 43738 | B56: 43738.459 | C56: Auction 3. Period CAP2-EU | D56: T3PA | E56: 25.03 | F56: 24.73 | G56: 29 | H56: 25.13 | I56: 25.02 | J56: 2744500 | K56: 4298500 | L56: 81 | M56: 38 | N56: 4.05 | O56: 53068 | P56: 214925 | Q56: 390282 | R56: 161441 | S56: 295007 | T56: 1.57 | U56: 20 | V56: 17 | W56: 68694835 | X56: EU | Y56: 1376650 | Z56: 2678210 | AA56: 3303960 | AB56: 187725 | AC56: 4730670 | AE56: 1251500 | AF56: 1088805 | AG56: 3779530 | AH56: 9223555 | AI56: 1639465 | AJ56: 5356420 | AK56: 538145 | AL56: 1714555 | AM56: 913595 | AN56: 287845 | AO56: 9611520 | AP56: 12515 | AQ56: 625750 | AR56: 125150 | AS56: 312875 | AT56: 125150 | AU56: 3278930 | AV56: 5694325 | AX56: 1914795 | AY56: 5631750 | AZ56: 951140 | BA56: 500600 | BB56: 1839705
A57: 43735 | B57: 43735.459 | C57: Auction 3. Period DE | D57: T3PA | E57: 25.3 | F57: 25 | G57: 30.01 | H57: 25.47 | I57: 25.25 | J57: 2834500 | K57: 4796500 | L57: 81 | M57: 31 | N57: 3.68 | O57: 59216 | P57: 218023 | Q57: 374764 | R57: 177156 | S57: 293799 | T57: 1.69 | U57: 22 | V57: 16 | W57: 71712850 | X57: DE | AD57: 71712850
A58: 43734 | B58: 43734.459 | C58: Auction 3. Period CAP2-EU | D58: T3PA | E58: 25.21 | F58: 24.88 | G58: 29 | H58: 25.36 | I58: 25.13 | J58: 2744500 | K58: 4737500 | L58: 82 | M58: 25 | N58: 4.1 | O58: 57774 | P58: 236875 | Q58: 369962 | R58: 196036 | S58: 261126 | T58: 1.73 | U58: 20 | V58: 14 | W58: 69188845 | X58: EU | Y58: 1386550 | Z58: 2697470 | AA58: 3327720 | AB58: 189075 | AC58: 4764690 | AE58: 1260500 | AF58: 1096635 | AG58: 3806710 | AH58: 9289885 | AI58: 1651255 | AJ58: 5394940 | AK58: 542015 | AL58: 1726885 | AM58: 920165 | AN58: 289915 | AO58: 9680640 | AP58: 12605 | AQ58: 630250 | AR58: 126050 | AS58: 315125 | AT58: 126050 | AU58: 3302510 | AV58: 5735275 | AX58: 1928565 | AY58: 5672250 | AZ58: 957980 | BA58: 504200 | BB58: 1852935
A59: 43733 | B59: 43733.459 | C59: Auction 3. Period CAP2-PL | D59: T3PA | E59: 25.17 | F59: 24.68 | G59: 29 | H59: 25.25 | I59: 25.07 | J59: 4714500 | K59: 7782000 | L59: 107 | M59: 34 | N59: 4.28 | O59: 72729 | P59: 311280 | Q59: 494112 | R59: 277324 | S59: 392394 | T59: 1.65 | U59: 25 | V59: 17 | W59: 118663965 | X59: PL | AW59: 118663965
A60: 43732 | B60: 43732.459 | C60: Auction 3. Period CAP2-EU | D60: T3PA | E60: 25.59 | F60: 25.25 | G60: 29 | H60: 25.71 | I60: 25.55 | J60: 2744500 | K60: 4897500 | L60: 78 | M60: 29 | N60: 3.39 | O60: 62788 | P60: 212935 | Q60: 323463 | R60: 171531 | S60: 255671 | T60: 1.78 | U60: 23 | V60: 16 | W60: 70231755 | X60: EU | Y60: 1407450 | Z60: 2738130 | AA60: 3377880 | AB60: 191925 | AC60: 4836510 | AE60: 1279500 | AF60: 1113165 | AG60: 3864090 | AH60: 9429915 | AI60: 1676145 | AJ60: 5476260 | AK60: 550185 | AL60: 1752915 | AM60: 934035 | AN60: 294285 | AO60: 9826560 | AP60: 12795 | AQ60: 639750 | AR60: 127950 | AS60: 319875 | AT60: 127950 | AU60: 3352290 | AV60: 5821725 | AX60: 1957635 | AY60: 5757750 | AZ60: 972420 | BA60: 511800 | BB60: 1880865
A61: 43731 | B61: 43731.459 | C61: Auction 3. Period CAP2-EU | D61: T3PA | E61: 25.93 | F61: 25.64 | G61: 29 | H61: 26.03 | I61: 25.92 | J61: 2744500 | K61: 4532000 | L61: 86 | M61: 33 | N61: 4.53 | O61: 52698 | P61: 238526 | Q61: 354318 | R61: 161441 | S61: 270196 | T61: 1.65 | U61: 19 | V61: 17 | W61: 71164885 | X61: EU | Y61: 1426150 | Z61: 2774510 | AA61: 3422760 | AB61: 194475 | AC61: 4900770 | AE61: 1296500 | AF61: 1127955 | AG61: 3915430 | AH61: 9555205 | AI61: 1698415 | AJ61: 5549020 | AK61: 557495 | AL61: 1776205 | AM61: 946445 | AN61: 298195 | AO61: 9957120 | AP61: 12965 | AQ61: 648250 | AR61: 129650 | AS61: 324125 | AT61: 129650 | AU61: 3396830 | AV61: 5899075 | AX61: 1983645 | AY61: 5834250 | AZ61: 985340 | BA61: 518600 | BB61: 1905855
A62: 43728 | B62: 43728.459 | C62: Auction 3. Period DE | D62: T3PA | E62: 26.17 | F62: 24 | G62: 29 | H62: 26.28 | I62: 26.18 | J62: 2834500 | K62: 3900000 | L62: 62 | M62: 35 | N62: 3.26 | O62: 62903 | P62: 205263 | Q62: 299118 | R62: 188967 | S62: 233817 | T62: 1.38 | U62: 19 | V62: 15 | W62: 74178865 | X62: DE | AD62: 74178865
A63: 43727 | B63: 43727.459 | C63: Auction 3. Period CAP2-EU | D63: T3PA | E63: 25.56 | F63: 24 | G63: 28 | H63: 25.51 | I63: 25.42 | J63: 2744500 | K63: 5937000 | L63: 100 | M63: 27 | N63: 3.7 | O63: 59370 | P63: 219889 | Q63: 345227 | R63: 171531 | S63: 244529 | T63: 2.16 | U63: 27 | V63: 16 | W63: 70149420 | X63: EU | Y63: 1405800 | Z63: 2734920 | AA63: 3373920 | AB63: 191700 | AC63: 4830840 | AE63: 1278000 | AF63: 1111860 | AG63: 3859560 | AH63: 9418860 | AI63: 1674180 | AJ63: 5469840 | AK63: 549540 | AL63: 1750860 | AM63: 932940 | AN63: 293940 | AO63: 9815040 | AP63: 12780 | AQ63: 639000 | AR63: 127800 | AS63: 319500 | AT63: 127800 | AU63: 3348360 | AV63: 5814900 | AX63: 1955340 | AY63: 5751000 | AZ63: 971280 | BA63: 511200 | BB63: 1878660
A64: 43725 | B64: 43725.459 | C64: Auction 3. Period CAP2-EU | D64: T3PA | E64: 26.75 | F64: 24 | G64: 29 | H64: 26.74 | I64: 26.56 | J64: 2744500 | K64: 5769500 | L64: 94 | M64: 19 | N64: 3.48 | O64: 61378 | P64: 213685 | Q64: 282146 | R64: 228708 | S64: 269015 | T64: 2.1 | U64: 27 | V64: 12 | W64: 73415375 | X64: EU | Y64: 1471250 | Z64: 2862250 | AA64: 3531000 | AB64: 200625 | AC64: 5055750 | AE64: 1337500 | AF64: 1163625 | AG64: 4039250 | AH64: 9857375 | AI64: 1752125 | AJ64: 5724500 | AK64: 575125 | AL64: 1832375 | AM64: 976375 | AN64: 307625 | AO64: 10272000 | AP64: 13375 | AQ64: 668750 | AR64: 133750 | AS64: 334375 | AT64: 133750 | AU64: 3504250 | AV64: 6085625 | AX64: 2046375 | AY64: 6018750 | AZ64: 1016500 | BA64: 535000 | BB64: 1966125
A65: 43724 | B65: 43724.459 | C65: Auction 3. Period CAP2-EU | D65: T3PA | E65: 26.58 | F65: 24 | G65: 28 | H65: 26.56 | I65: 26.51 | J65: 2744500 | K65: 4616500 | L65: 76 | M65: 23 | N65: 3.3 | O65: 60743 | P65: 200717 | Q65: 361290 | R65: 211115 | S65: 305678 | T65: 1.68 | U65: 23 | V65: 13 | W65: 72948810 | X65: EU | Y65: 1461900 | Z65: 2844060 | AA65: 3508560 | AB65: 199350 | AC65: 5023620 | AE65: 1329000 | AF65: 1156230 | AG65: 4013580 | AH65: 9794730 | AI65: 1740990 | AJ65: 5688120 | AK65: 571470 | AL65: 1820730 | AM65: 970170 | AN65: 305670 | AO65: 10206720 | AP65: 13290 | AQ65: 664500 | AR65: 132900 | AS65: 332250 | AT65: 132900 | AU65: 3481980 | AV65: 6046950 | AX65: 2033370 | AY65: 5980500 | AZ65: 1010040 | BA65: 531600 | BB65: 1953630
A66: 43721 | B66: 43721.459 | C66: Auction 3. Period DE | D66: T3PA | E66: 26.22 | F66: 22.4 | G66: 28 | H66: 26.12 | I66: 26.11 | J66: 2834500 | K66: 5116000 | L66: 95 | M66: 24 | N66: 4.32 | O66: 53853 | P66: 232545 | Q66: 295807 | R66: 166735 | S66: 197257 | T66: 1.8 | U66: 22 | V66: 17 | W66: 74320590 | X66: DE | AD66: 74320590
A67: 43720 | B67: 43720.459 | C67: Auction 3. Period CAP2-EU | D67: T3PA | E67: 26.55 | F67: 26 | G67: 28 | H67: 26.52 | I67: 26.38 | J67: 2744500 | K67: 5089500 | L67: 78 | M67: 20 | N67: 3.55 | O67: 65250 | P67: 231341 | Q67: 271662 | R67: 228708 | S67: 267884 | T67: 1.85 | U67: 22 | V67: 12 | W67: 72866475 | X67: EU | Y67: 1460250 | Z67: 2840850 | AA67: 3504600 | AB67: 199125 | AC67: 5017950 | AE67: 1327500 | AF67: 1154925 | AG67: 4009050 | AH67: 9783675 | AI67: 1739025 | AJ67: 5681700 | AK67: 570825 | AL67: 1818675 | AM67: 969075 | AN67: 305325 | AO67: 10195200 | AP67: 13275 | AQ67: 663750 | AR67: 132750 | AS67: 331875 | AT67: 132750 | AU67: 3478050 | AV67: 6040125 | AX67: 2031075 | AY67: 5973750 | AZ67: 1008900 | BA67: 531000 | BB67: 1951425
A68: 43719 | B68: 43719.625 | C68: EUAA Auction CAP2-EU | D68: EAA3 | E68: 26.34 | F68: 25.95 | G68: 26.59 | H68: 26.37 | I68: 26.39 | J68: 892000 | K68: 1320000 | L68: 36 | M68: 24 | N68: 4.5 | O68: 36667 | P68: 165000 | Q68: 163917 | R68: 127429 | S68: 138949 | T68: 1.48 | U68: 8 | V68: 7 | W68: 23495280 | X68: EU | Y68: 500460 | Z68: 579480 | AA68: 197550 | AB68: 302910 | AC68: 250230 | AE68: 579480 | AF68: 39510 | AG68: 1066770 | AH68: 3476880 | AI68: 447780 | AJ68: 2594490 | AK68: 131700 | AL68: 210720 | AM68: 460950 | AN68: 618990 | AO68: 3068610 | AP68: 0 | AQ68: 65850 | AR68: 52680 | AS68: 118530 | AT68: 118530 | AU68: 790200 | AV68: 6018690 | AX68: 618990 | AY68: 342420 | AZ68: 777030 | BA68: 26340 | BB68: 39510
A69: 43719 | B69: 43719.459 | C69: Auction 3. Period CAP2-PL | D69: T3PA | E69: 26.68 | F69: 24 | G69: 30.01 | H69: 26.83 | I69: 26.65 | J69: 4714500 | K69: 6153500 | L69: 81 | M69: 37 | N69: 4.5 | O69: 75969 | P69: 341861 | Q69: 408493 | R69: 294656 | S69: 397560 | T69: 1.31 | U69: 18 | V69: 16 | W69: 125782860 | X69: PL | AW69: 125782860
A70: 43718 | B70: 43718.459 | C70: Auction 3. Period CAP2-EU | D70: T3PA | E70: 25.5 | F70: 24 | G70: 29 | H70: 25.54 | I70: 25.46 | J70: 2744500 | K70: 4993500 | L70: 77 | M70: 32 | N70: 2.96 | O70: 64851 | P70: 192058 | Q70: 308149 | R70: 130690 | S70: 229748 | T70: 1.82 | U70: 26 | V70: 21 | W70: 69984750 | X70: EU | Y70: 1402500 | Z70: 2728500 | AA70: 3366000 | AB70: 191250 | AC70: 4819500 | AE70: 1275000 | AF70: 1109250 | AG70: 3850500 | AH70: 9396750 | AI70: 1670250 | AJ70: 5457000 | AK70: 548250 | AL70: 1746750 | AM70: 930750 | AN70: 293250 | AO70: 9792000 | AP70: 12750 | AQ70: 637500 | AR70: 127500 | AS70: 318750 | AT70: 127500 | AU70: 3340500 | AV70: 5801250 | AX70: 1950750 | AY70: 5737500 | AZ70: 969000 | BA70: 510000 | BB70: 1874250
A71: 43717 | B71: 43717.459 | C71: Auction 3. Period CAP2-EU | D71: T3PA | E71: 25.01 | F71: 24 | G71: 29 | H71: 25.1 | I71: 24.96 | J71: 2744500 | K71: 5471500 | L71: 62 | M71: 24 | N71: 2.7 | O71: 88250 | P71: 237891 | Q71: 320507 | R71: 161441 | S71: 226878 | T71: 1.99 | U71: 23 | V71: 17 | W71: 68639945 | X71: EU | Y71: 1375550 | Z71: 2676070 | AA71: 3301320 | AB71: 187575 | AC71: 4726890 | AE71: 1250500 | AF71: 1087935 | AG71: 3776510 | AH71: 9216185 | AI71: 1638155 | AJ71: 5352140 | AK71: 537715 | AL71: 1713185 | AM71: 912865 | AN71: 287615 | AO71: 9603840 | AP71: 12505 | AQ71: 625250 | AR71: 125050 | AS71: 312625 | AT71: 125050 | AU71: 3276310 | AV71: 5689775 | AX71: 1913265 | AY71: 5627250 | AZ71: 950380 | BA71: 500200 | BB71: 1838235
A72: 43714 | B72: 43714.459 | C72: Auction 3. Period DE | D72: T3PA | E72: 25.46 | F72: 23.9 | G72: 29 | H72: 25.44 | I72: 25.35 | J72: 2834500 | K72: 8087500 | L72: 77 | M72: 27 | N72: 3.08 | O72: 105032 | P72: 323500 | Q72: 594334 | R72: 149184 | S72: 263438 | T72: 2.85 | U72: 25 | V72: 19 | W72: 72166370 | X72: DE | AD72: 72166370
A73: 43711 | B73: 43711.459 | C73: Auction 3. Period CAP2-EU | D73: T3PA | E73: 24.82 | F73: 24.2 | G73: 29 | H73: 24.86 | I73: 24.7 | J73: 2744500 | K73: 5576500 | L73: 79 | M73: 25 | N73: 3.29 | O73: 70589 | P73: 232354 | Q73: 334150 | R73: 161441 | S73: 255980 | T73: 2.03 | U73: 24 | V73: 17 | W73: 68118490 | X73: EU | Y73: 1365100 | Z73: 2655740 | AA73: 3276240 | AB73: 186150 | AC73: 4690980 | AE73: 1241000 | AF73: 1079670 | AG73: 3747820 | AH73: 9146170 | AI73: 1625710 | AJ73: 5311480 | AK73: 533630 | AL73: 1700170 | AM73: 905930 | AN73: 285430 | AO73: 9530880 | AP73: 12410 | AQ73: 620500 | AR73: 124100 | AS73: 310250 | AT73: 124100 | AU73: 3251420 | AV73: 5646550 | AX73: 1898730 | AY73: 5584500 | AZ73: 943160 | BA73: 496400 | BB73: 1824270
A74: 43710 | B74: 43710.459 | C74: Auction 3. Period CAP2-EU | D74: T3PA | E74: 25.4 | F74: 25 | G74: 27 | H74: 25.47 | I74: 25.32 | J74: 2744500 | K74: 4761500 | L74: 71 | M74: 24 | N74: 3.23 | O74: 67063 | P74: 216432 | Q74: 254102 | R74: 171531 | S74: 198897 | T74: 1.73 | U74: 22 | V74: 16 | W74: 69710300 | X74: EU | Y74: 1397000 | Z74: 2717800 | AA74: 3352800 | AB74: 190500 | AC74: 4800600 | AE74: 1270000 | AF74: 1104900 | AG74: 3835400 | AH74: 9359900 | AI74: 1663700 | AJ74: 5435600 | AK74: 546100 | AL74: 1739900 | AM74: 927100 | AN74: 292100 | AO74: 9753600 | AP74: 12700 | AQ74: 635000 | AR74: 127000 | AS74: 317500 | AT74: 127000 | AU74: 3327400 | AV74: 5778500 | AX74: 1943100 | AY74: 5715000 | AZ74: 965200 | BA74: 508000 | BB74: 1866900
A75: 43707 | B75: 43707.459 | C75: Auction 3. Period DE | D75: T3PA | E75: 26.8 | F75: 23.31 | G75: 28 | H75: 26.58 | I75: 26.66 | J75: 1604500 | K75: 3501000 | L75: 64 | M75: 15 | N75: 2.78 | O75: 54703 | P75: 152217 | Q75: 283218 | R75: 123423 | S75: 203849 | T75: 2.18 | U75: 23 | V75: 13 | W75: 43000600 | X75: DE | AD75: 43000600
A76: 43706 | B76: 43706.459 | C76: Auction 3. Period CAP2-EU | D76: T3PA | E76: 25.93 | F76: 23.23 | G76: 29 | H76: 25.89 | I76: 25.85 | J76: 1505500 | K76: 3087000 | L76: 74 | M76: 23 | N76: 3.08 | O76: 41716 | P76: 128625 | Q76: 128767 | R76: 94094 | S76: 87884 | T76: 2.05 | U76: 24 | V76: 16 | W76: 39037615 | X76: EU | Y76: 777900 | Z76: 1529870 | AA76: 1802135 | AB76: 168545 | AC76: 3280145 | AE76: 557495 | AF76: 583425 | AG76: 2035505 | AH76: 5315650 | AI76: 1283535 | AJ76: 2943055 | AK76: 375985 | AL76: 1127955 | AM76: 401915 | AN76: 168545 | AO76: 5082280 | AQ76: 453775 | AR76: 38895 | AS76: 298195 | AT76: 116685 | AU76: 1970680 | AV76: 3461655 | AX76: 1011270 | AY76: 3137530 | AZ76: 168545 | BA76: 38895 | BB76: 907550
A77: 43705 | B77: 43705.459 | C77: Auction 3. Period CAP2-PL | D77: T3PA | E77: 26 | F77: 23.34 | G77: 29 | H77: 25.94 | I77: 25.85 | J77: 2214500 | K77: 4482500 | L77: 74 | M77: 20 | N77: 3.22 | O77: 60574 | P77: 194891 | Q77: 289272 | R77: 147633 | S77: 203212 | T77: 2.02 | U77: 23 | V77: 15 | W77: 57577000 | X77: PL | AW77: 57577000
A78: 43704 | B78: 43704.459 | C78: Auction 3. Period CAP2-EU | D78: T3PA | E78: 25.25 | F78: 23.39 | G78: 28 | H78: 25.32 | I78: 25.18 | J78: 1387500 | K78: 2835500 | L78: 73 | M78: 28 | N78: 3.04 | O78: 38842 | P78: 118146 | Q78: 133676 | R78: 77083 | S78: 75740 | T78: 2.04 | U78: 24 | V78: 18 | W78: 35034375 | X78: EU | Y78: 681750 | Z78: 1338250 | AA78: 1666500 | AB78: 113625 | AC78: 2373500 | AE78: 606000 | AF78: 530250 | AG78: 1906375 | AH78: 4658625 | AI78: 820625 | AJ78: 2701750 | AK78: 277750 | AL78: 858500 | AM78: 454500 | AN78: 164125 | AO78: 4797500 | AQ78: 340875 | AR78: 75750 | AS78: 164125 | AT78: 25250 | AU78: 1653875 | AV78: 3370875 | AX78: 959500 | AY78: 2840625 | AZ78: 479750 | BA78: 227250 | BB78: 946875
A79: 43700 | B79: 43700.459 | C79: Auction 3. Period DE | D79: T3PA | E79: 25.33 | F79: 23.42 | G79: 29 | H79: 25.4 | I79: 25.34 | J79: 1604500 | K79: 2953000 | L79: 76 | M79: 40 | N79: 3.45 | O79: 38855 | P79: 134227 | Q79: 242809 | R79: 89139 | S79: 129355 | T79: 1.84 | U79: 22 | V79: 18 | W79: 40641985 | X79: DE | AD79: 40641985
A80: 43699 | B80: 43699.459 | C80: Auction 3. Period CAP2-EU | D80: T3PA | E80: 25.78 | F80: 23.43 | G80: 29 | H80: 25.74 | I80: 25.73 | J80: 1387500 | K80: 3994500 | L80: 91 | M80: 36 | N80: 3.37 | O80: 43896 | P80: 147944 | Q80: 274234 | R80: 63068 | S80: 75776 | T80: 2.88 | U80: 27 | V80: 22 | W80: 35769750 | X80: EU | Y80: 696060 | Z80: 1366340 | AA80: 1701480 | AB80: 116010 | AC80: 2423320 | AE80: 618720 | AF80: 541380 | AG80: 1946390 | AH80: 4756410 | AI80: 837850 | AJ80: 2758460 | AK80: 283580 | AL80: 876520 | AM80: 464040 | AN80: 167570 | AO80: 4898200 | AQ80: 348030 | AR80: 77340 | AS80: 167570 | AT80: 25780 | AU80: 1688590 | AV80: 3441630 | AX80: 979640 | AY80: 2900250 | AZ80: 489820 | BA80: 232020 | BB80: 966750
A81: 43697 | B81: 43697.459 | C81: Auction 3. Period CAP2-EU | D81: T3PA | E81: 26.94 | F81: 23.35 | G81: 29 | H81: 26.7 | I81: 26.77 | J81: 1387500 | K81: 3437000 | L81: 77 | M81: 18 | N81: 3.35 | O81: 44636 | P81: 149435 | Q81: 250668 | R81: 92500 | S81: 167664 | T81: 2.48 | U81: 23 | V81: 15 | W81: 37379250 | X81: EU | Y81: 727380 | Z81: 1427820 | AA81: 1778040 | AB81: 121230 | AC81: 2532360 | AE81: 646560 | AF81: 565740 | AG81: 2033970 | AH81: 4970430 | AI81: 875550 | AJ81: 2882580 | AK81: 296340 | AL81: 915960 | AM81: 484920 | AN81: 175110 | AO81: 5118600 | AQ81: 363690 | AR81: 80820 | AS81: 175110 | AT81: 26940 | AU81: 1764570 | AV81: 3596490 | AX81: 1023720 | AY81: 3030750 | AZ81: 511860 | BA81: 242460 | BB81: 1010250
A82: 43696 | B82: 43696.459 | C82: Auction 3. Period CAP2-EU | D82: T3PA | E82: 26.25 | F82: 23.45 | G82: 29 | H82: 26.11 | I82: 26.08 | J82: 1387500 | K82: 4065500 | L82: 97 | M82: 20 | N82: 3.59 | O82: 41912 | P82: 150574 | Q82: 242099 | R82: 81618 | S82: 135437 | T82: 2.93 | U82: 27 | V82: 17 | W82: 36421875 | X82: EU | Y82: 708750 | Z82: 1391250 | AA82: 1732500 | AB82: 118125 | AC82: 2467500 | AE82: 630000 | AF82: 551250 | AG82: 1981875 | AH82: 4843125 | AI82: 853125 | AJ82: 2808750 | AK82: 288750 | AL82: 892500 | AM82: 472500 | AN82: 170625 | AO82: 4987500 | AQ82: 354375 | AR82: 78750 | AS82: 170625 | AT82: 26250 | AU82: 1719375 | AV82: 3504375 | AX82: 997500 | AY82: 2953125 | AZ82: 498750 | BA82: 236250 | BB82: 984375
A83: 43693 | B83: 43693.459 | C83: Auction 3. Period DE | D83: T3PA | E83: 26.12 | F83: 25 | G83: 29 | H83: 26.13 | I83: 26.04 | J83: 1604500 | K83: 4579000 | L83: 86 | M83: 28 | N83: 3.58 | O83: 53244 | P83: 190792 | Q83: 361460 | R83: 94382 | S83: 150449 | T83: 2.85 | U83: 24 | V83: 17 | W83: 41909540 | X83: DE | AD83: 41909540
A84: 43692 | B84: 43692.459 | C84: Auction 3. Period CAP2-EU | D84: T3PA | E84: 26.41 | F84: 25 | G84: 28 | H84: 26.42 | I84: 26.38 | J84: 1387500 | K84: 2806500 | L84: 69 | M84: 30 | N84: 3.45 | O84: 40674 | P84: 140325 | Q84: 134272 | R84: 86719 | S84: 92907 | T84: 2.02 | U84: 20 | V84: 16 | W84: 36643875 | X84: EU | Y84: 713070 | Z84: 1399730 | AA84: 1743060 | AB84: 118845 | AC84: 2482540 | AE84: 633840 | AF84: 554610 | AG84: 1993955 | AH84: 4872645 | AI84: 858325 | AJ84: 2825870 | AK84: 290510 | AL84: 897940 | AM84: 475380 | AN84: 171665 | AO84: 5017900 | AQ84: 356535 | AR84: 79230 | AS84: 171665 | AT84: 26410 | AU84: 1729855 | AV84: 3525735 | AX84: 1003580 | AY84: 2971125 | AZ84: 501790 | BA84: 237690 | BB84: 990375
A85: 43691 | B85: 43691.459 | C85: Auction 3. Period CAP2-PL | D85: T3PA | E85: 27.15 | F85: 25 | G85: 30 | H85: 27.13 | I85: 27.1 | J85: 2214500 | K85: 3709500 | L85: 68 | M85: 25 | N85: 2.96 | O85: 54551 | P85: 161283 | Q85: 165566 | R85: 130265 | S85: 127490 | T85: 1.68 | U85: 23 | V85: 17 | W85: 60123675 | X85: PL | AW85: 60123675
A86: 43690 | B86: 43690.459 | C86: Auction 3. Period CAP2-EU | D86: T3PA | E86: 27.1 | F86: 23.59 | G86: 30.01 | H86: 26.78 | I86: 26.76 | J86: 1387500 | K86: 3944500 | L86: 92 | M86: 12 | N86: 3.29 | O86: 42875 | P86: 140875 | Q86: 220369 | R86: 115625 | S86: 182492 | T86: 2.84 | U86: 28 | V86: 12 | W86: 37601250 | X86: EU | Y86: 731700 | Z86: 1436300 | AA86: 1788600 | AB86: 121950 | AC86: 2547400 | AE86: 650400 | AF86: 569100 | AG86: 2046050 | AH86: 4999950 | AI86: 880750 | AJ86: 2899700 | AK86: 298100 | AL86: 921400 | AM86: 487800 | AN86: 176150 | AO86: 5149000 | AQ86: 365850 | AR86: 81300 | AS86: 176150 | AT86: 27100 | AU86: 1775050 | AV86: 3617850 | AX86: 1029800 | AY86: 3048750 | AZ86: 514900 | BA86: 243900 | BB86: 1016250
A87: 43689 | B87: 43689.459 | C87: Auction 3. Period CAP2-EU | D87: T3PA | E87: 27.7 | F87: 25 | G87: 30 | H87: 27.74 | I87: 27.69 | J87: 1387500 | K87: 4130000 | L87: 83 | M87: 40 | N87: 3.77 | O87: 49759 | P87: 187727 | Q87: 316975 | R87: 73026 | S87: 97827 | T87: 2.98 | U87: 22 | V87: 19 | W87: 38433750 | X87: EU | Y87: 747900 | Z87: 1468100 | AA87: 1828200 | AB87: 124650 | AC87: 2603800 | AE87: 664800 | AF87: 581700 | AG87: 2091350 | AH87: 5110650 | AI87: 900250 | AJ87: 2963900 | AK87: 304700 | AL87: 941800 | AM87: 498600 | AN87: 180050 | AO87: 5263000 | AQ87: 373950 | AR87: 83100 | AS87: 180050 | AT87: 27700 | AU87: 1814350 | AV87: 3697950 | AX87: 1052600 | AY87: 3116250 | AZ87: 526300 | BA87: 249300 | BB87: 1038750
A88: 43686 | B88: 43686.459 | C88: Auction 3. Period DE | D88: T3PA | E88: 28.37 | F88: 23.65 | G88: 30 | H88: 28.21 | I88: 28.36 | J88: 1604500 | K88: 3705500 | L88: 80 | M88: 39 | N88: 3.64 | O88: 46319 | P88: 168432 | Q88: 292092 | R88: 94382 | S88: 107165 | T88: 2.31 | U88: 22 | V88: 17 | W88: 45519665 | X88: DE | AD88: 45519665
A89: 43685 | B89: 43685.459 | C89: Auction 3. Period CAP2-EU | D89: T3PA | E89: 28.68 | F89: 25 | G89: 35 | H89: 28.51 | I89: 28.5 | J89: 1387500 | K89: 4059500 | L89: 80 | M89: 15 | N89: 3.33 | O89: 50744 | P89: 169146 | Q89: 251772 | R89: 99107 | S89: 154503 | T89: 2.93 | U89: 24 | V89: 14 | W89: 39793500 | X89: EU | Y89: 774360 | Z89: 1520040 | AA89: 1892880 | AB89: 129060 | AC89: 2695920 | AE89: 688320 | AF89: 602280 | AG89: 2165340 | AH89: 5291460 | AI89: 932100 | AJ89: 3068760 | AK89: 315480 | AL89: 975120 | AM89: 516240 | AN89: 186420 | AO89: 5449200 | AQ89: 387180 | AR89: 86040 | AS89: 186420 | AT89: 28680 | AU89: 1878540 | AV89: 3828780 | AX89: 1089840 | AY89: 3226500 | AZ89: 544920 | BA89: 258120 | BB89: 1075500
A90: 43683 | B90: 43683.459 | C90: Auction 3. Period CAP2-EU | D90: T3PA | E90: 28.48 | F90: 25 | G90: 31 | H90: 28.27 | I90: 28.27 | J90: 1387500 | K90: 4948500 | L90: 99 | M90: 19 | N90: 3.67 | O90: 49985 | P90: 183278 | Q90: 268276 | R90: 77083 | S90: 103651 | T90: 3.57 | U90: 27 | V90: 18 | W90: 39516000 | X90: EU | Y90: 768960 | Z90: 1509440 | AA90: 1879680 | AB90: 128160 | AC90: 2677120 | AE90: 683520 | AF90: 598080 | AG90: 2150240 | AH90: 5254560 | AI90: 925600 | AJ90: 3047360 | AK90: 313280 | AL90: 968320 | AM90: 512640 | AN90: 185120 | AO90: 5411200 | AQ90: 384480 | AR90: 85440 | AS90: 185120 | AT90: 28480 | AU90: 1865440 | AV90: 3802080 | AX90: 1082240 | AY90: 3204000 | AZ90: 541120 | BA90: 256320 | BB90: 1068000
A91: 43682 | B91: 43682.459 | C91: Auction 3. Period CAP2-EU | D91: T3PA | E91: 28.82 | F91: 25 | G91: 31 | H91: 28.66 | I91: 28.69 | J91: 1387500 | K91: 3622500 | L91: 81 | M91: 21 | N91: 3.68 | O91: 44722 | P91: 164659 | Q91: 268299 | R91: 81618 | S91: 104082 | T91: 2.61 | U91: 22 | V91: 17 | W91: 39987750 | X91: EU | Y91: 778140 | Z91: 1527460 | AA91: 1902120 | AB91: 129690 | AC91: 2709080 | AE91: 691680 | AF91: 605220 | AG91: 2175910 | AH91: 5317290 | AI91: 936650 | AJ91: 3083740 | AK91: 317020 | AL91: 979880 | AM91: 518760 | AN91: 187330 | AO91: 5475800 | AQ91: 389070 | AR91: 86460 | AS91: 187330 | AT91: 28820 | AU91: 1887710 | AV91: 3847470 | AX91: 1095160 | AY91: 3242250 | AZ91: 547580 | BA91: 259380 | BB91: 1080750
A92: 43679 | B92: 43679.459 | C92: Auction 3. Period DE | D92: T3PA | E92: 29.1 | F92: 25 | G92: 30 | H92: 28.92 | I92: 29.02 | J92: 1604500 | K92: 4604000 | L92: 81 | M92: 27 | N92: 3.38 | O92: 56840 | P92: 191833 | Q92: 347727 | R92: 100281 | S92: 165871 | T92: 2.87 | U92: 24 | V92: 16 | W92: 46690950 | X92: DE | AD92: 46690950
A93: 43678 | B93: 43678.459 | C93: Auction 3. Period CAP2-EU | D93: T3PA | E93: 28.9 | F93: 25 | G93: 31 | H93: 28.61 | I93: 28.69 | J93: 1387500 | K93: 4658500 | L93: 92 | M93: 19 | N93: 3.17 | O93: 50636 | P93: 160638 | Q93: 239441 | R93: 81618 | S93: 81974 | T93: 3.36 | U93: 29 | V93: 17 | W93: 40098750 | X93: EU | Y93: 780300 | Z93: 1531700 | AA93: 1907400 | AB93: 130050 | AC93: 2716600 | AE93: 693600 | AF93: 606900 | AG93: 2181950 | AH93: 5332050 | AI93: 939250 | AJ93: 3092300 | AK93: 317900 | AL93: 982600 | AM93: 520200 | AN93: 187850 | AO93: 5491000 | AQ93: 390150 | AR93: 86700 | AS93: 187850 | AT93: 28900 | AU93: 1892950 | AV93: 3858150 | AX93: 1098200 | AY93: 3251250 | AZ93: 549100 | BA93: 260100 | BB93: 1083750
A94: 43677 | B94: 43677.459 | C94: Auction 3. Period CAP2-PL | D94: T3PA | E94: 28.04 | F94: 25 | G94: 30 | H94: 27.99 | I94: 27.97 | J94: 4428500 | K94: 8722500 | L94: 97 | M94: 36 | N94: 4.22 | O94: 89923 | P94: 379239 | Q94: 705591 | R94: 260500 | S94: 486903 | T94: 1.97 | U94: 23 | V94: 17 | W94: 124175140 | X94: PL | AW94: 124175140
A95: 43676 | B95: 43676.459 | C95: Auction 3. Period CAP2-EU | D95: T3PA | E95: 28.18 | F95: 22.86 | G95: 30 | H95: 28.02 | I95: 28.1 | J95: 2775000 | K95: 5881500 | L95: 94 | M95: 31 | N95: 3.76 | O95: 62569 | P95: 235260 | Q95: 415833 | R95: 163235 | S95: 208979 | T95: 2.12 | U95: 25 | V95: 17 | W95: 78199500 | X95: EU | Y95: 1521720 | Z95: 2987080 | AA95: 3719760 | AB95: 197260 | AC95: 5326020 | AE95: 1366730 | AF95: 1197650 | AG95: 4269270 | AH95: 10384330 | AI95: 1831700 | AJ95: 6030520 | AK95: 605870 | AL95: 1916240 | AM95: 1028570 | AN95: 366340 | AO95: 10764760 | AP95: 0 | AQ95: 704500 | AR95: 140900 | AS95: 352250 | AT95: 126810 | AU95: 3691580 | AV95: 7524060 | AX95: 2141680 | AY95: 6340500 | AZ95: 1042660 | BA95: 549510 | BB95: 2071230
A96: 43675 | B96: 43675.459 | C96: Auction 3. Period CAP2-EU | D96: T3PA | E96: 28.8 | F96: 22.96 | G96: 31.01 | H96: 28.65 | I96: 28.71 | J96: 2775000 | K96: 5290000 | L96: 89 | M96: 30 | N96: 3.3 | O96: 59438 | P96: 195926 | Q96: 273731 | R96: 138750 | S96: 193114 | T96: 1.91 | U96: 27 | V96: 20 | W96: 79920000 | X96: EU | Y96: 1555200 | Z96: 3052800 | AA96: 3801600 | AB96: 201600 | AC96: 5443200 | AE96: 1396800 | AF96: 1224000 | AG96: 4363200 | AH96: 10612800 | AI96: 1872000 | AJ96: 6163200 | AK96: 619200 | AL96: 1958400 | AM96: 1051200 | AN96: 374400 | AO96: 11001600 | AP96: 0 | AQ96: 720000 | AR96: 144000 | AS96: 360000 | AT96: 129600 | AU96: 3772800 | AV96: 7689600 | AX96: 2188800 | AY96: 6480000 | AZ96: 1065600 | BA96: 561600 | BB96: 2116800
A97: 43672 | B97: 43672.459 | C97: Auction 3. Period DE | D97: T3PA | E97: 28.51 | F97: 23.02 | G97: 30 | H97: 28.24 | I97: 28.44 | J97: 3209000 | K97: 5547000 | L97: 87 | M97: 30 | N97: 3.78 | O97: 63759 | P97: 241174 | Q97: 402616 | R97: 178278 | S97: 283976 | T97: 1.73 | U97: 23 | V97: 18 | W97: 91488590 | X97: DE | AD97: 91488590
A98: 43671 | B98: 43671.459 | C98: Auction 3. Period CAP2-EU | D98: T3PA | E98: 29.46 | F98: 23.04 | G98: 30.5 | H98: 29.1 | I98: 29.42 | J98: 2775000 | K98: 6613000 | L98: 83 | M98: 38 | N98: 3.46 | O98: 79675 | P98: 275542 | Q98: 551358 | R98: 154167 | S98: 316524 | T98: 2.38 | U98: 24 | V98: 18 | W98: 81751500 | X98: EU | Y98: 1590840 | Z98: 3122760 | AA98: 3888720 | AB98: 206220 | AC98: 5567940 | AE98: 1428810 | AF98: 1252050 | AG98: 4463190 | AH98: 10856010 | AI98: 1914900 | AJ98: 6304440 | AK98: 633390 | AL98: 2003280 | AM98: 1075290 | AN98: 382980 | AO98: 11253720 | AP98: 0 | AQ98: 736500 | AR98: 147300 | AS98: 368250 | AT98: 132570 | AU98: 3859260 | AV98: 7865820 | AX98: 2238960 | AY98: 6628500 | AZ98: 1090020 | BA98: 574470 | BB98: 2165310
A99: 43669 | B99: 43669.459 | C99: Auction 3. Period CAP2-EU | D99: T3PA | E99: 29.05 | F99: 23.1 | G99: 32 | H99: 28.71 | I99: 28.89 | J99: 2775000 | K99: 7307000 | L99: 90 | M99: 23 | N99: 3.21 | O99: 81189 | P99: 260964 | Q99: 445168 | R99: 185000 | S99: 252682 | T99: 2.63 | U99: 28 | V99: 15 | W99: 80613750 | X99: EU | Y99: 1568700 | Z99: 3079300 | AA99: 3834600 | AB99: 203350 | AC99: 5490450 | AE99: 1408925 | AF99: 1234625 | AG99: 4401075 | AH99: 10704925 | AI99: 1888250 | AJ99: 6216700 | AK99: 624575 | AL99: 1975400 | AM99: 1060325 | AN99: 377650 | AO99: 11097100 | AP99: 0 | AQ99: 726250 | AR99: 145250 | AS99: 363125 | AT99: 130725 | AU99: 3805550 | AV99: 7756350 | AX99: 2207800 | AY99: 6536250 | AZ99: 1074850 | BA99: 566475 | BB99: 2135175
A100: 43668 | B100: 43668.459 | C100: Auction 3. Period CAP2-EU | D100: T3PA | E100: 28.96 | F100: 24 | G100: 35 | H100: 28.98 | I100: 29.02 | J100: 2775000 | K100: 3675500 | L100: 61 | M100: 41 | N100: 3.05 | O100: 60254 | P100: 183775 | Q100: 277491 | R100: 138750 | S100: 210273 | T100: 1.32 | U100: 20 | V100: 20 | W100: 80364000 | X100: EU | Y100: 1563840 | Z100: 3069760 | AA100: 3822720 | AB100: 202720 | AC100: 5473440 | AE100: 1404560 | AF100: 1230800 | AG100: 4387440 | AH100: 10671760 | AI100: 1882400 | AJ100: 6197440 | AK100: 622640 | AL100: 1969280 | AM100: 1057040 | AN100: 376480 | AO100: 11062720 | AP100: 0 | AQ100: 724000 | AR100: 144800 | AS100: 362000 | AT100: 130320 | AU100: 3793760 | AV100: 7732320 | AX100: 2200960 | AY100: 6516000 | AZ100: 1071520 | BA100: 564720 | BB100: 2128560
...

Sheet ETS price EEX 2022 Spot Primary
C1: Public
A2: More information
K3: EEX Emissions market / Primary Market Auction
A4: References | F4: Prices | K4: Volumes | V4: Participants | X4: Revenue | Z4: Revenue
A5: Date | B5: Time | C5: Auction Name | D5: Contract | E5: Status | F5: Auction Price €/tCO2 | G5: Minimum Bid €/tCO2 | H5: Maximum Bid €/tCO2 | I5: Mean €/tCO2 | J5: Median €/tCO2 | K5: Auction Volume tCO2 | L5: Total Amount of Bids | M5: Number of bids submitted | N5: Number of successful bids | O5: Average number of bids per bidder | P5: Average bid size | Q5: Average volume bid per bidder | R5: Standard deviation of bid volume per bidder | S5: Average volume won per bidder | T5: Standard deviation of volume won per bidder | U5: Cover Ratio | V5: Total Number of Bidders | W5: Number of Successful Bidders | X5: Total Revenue € | Y5: Country | Z5: Austria (AT) | AA5: Belgium (BE) | AB5: Bulgaria (BG) | AC5: Cyprus (CY) | AD5: Czech Republic (CZ) | AE5: Germany (DE) | AF5: Denmark (DK) | AG5: Estonia (EE) | AH5: Greece (EL) | AI5: Spain (ES) | AJ5: Finland (FI) | AK5: France (FR) | AL5: Croatia (HR) | AM5: Hungary (HU) | AN5: Ireland (IE) | AO5: Innovation Fund (IF) | AP5: Iceland (IS) | AQ5: Italy (IT) | AR5: Liechtenstein (LI) | AS5: Lithuania (LT) | AT5: Luxembourg (LU) | AU5: Latvia (LV) | AV5: Modernisation Fund (MF) | AW5: Malta (MT) | AX5: Netherlands (NL) | AY5: Norway (NO) | AZ5: Poland (PL) | BA5: Portugal (PT) | BB5: Romania (RO) | BC5: Sweden (SE) | BD5: Slovenia (SI) | BE5: Slovakia (SK) | BF5: Northern Ireland (XI)
A6: 44914 | B6: 44914.459 | C6: Auction 4. Period CAP3 EU | D6: T3PA | E6: successful | F6: 84.1 | G6: 75 | H6: 95 | I6: 85.95 | J6: 85.24 | K6: 2568500 | L6: 3235500 | M6: 63 | N6: 57 | O6: 3.94 | P6: 51357 | Q6: 202219 | R6: 276989 | S6: 197577 | T6: 280314 | U6: 1.26 | V6: 16 | W6: 13 | X6: 216010850 | Y6: EU | Z6: 2186600 | AA6: 5340350 | AB6: 9251000 | AC6: 1051250 | AD6: 6223400 | AF6: 3490150 | AG6: 1976350 | AH6: 10470450 | AI6: 25776650 | AJ6: 4457300 | AK6: 15095950 | AL6: 1219450 | AM6: 5760850 | AN6: 0 | AO6: 26071000 | AP6: 0 | AQ6: 26575600 | AR6: 42050 | AS6: 168200 | AT6: 0 | AU6: 1471750 | AV6: 42975100 | AW6: 798950 | AX6: 8704350 | AY6: 1555850 | BA6: 5172150 | BB6: 3700400 | BC6: 1345600 | BD6: 2018400 | BE6: 3111700
A7: 44911 | B7: 44911.459 | C7: Auction 4. Period DE | D7: T3PA | E7: successful | F7: 83.41 | G7: 45 | H7: 92 | I7: 83.57 | J7: 83.7 | K7: 1865500 | L7: 4316500 | M7: 83 | N7: 51 | O7: 4.61 | P7: 52006 | Q7: 239806 | R7: 346218 | S7: 116594 | T7: 153157 | U7: 2.31 | V7: 18 | W7: 16 | X7: 155601355 | Y7: DE | AE7: 155601355
A8: 44910 | B8: 44910.459 | C8: Auction 4. Period CAP3 EU | D8: T3PA | E8: successful | F8: 86.16 | G8: 45 | H8: 92.01 | I8: 85.59 | J8: 86.15 | K8: 2510500 | L8: 4378500 | M8: 66 | N8: 31 | O8: 3.88 | P8: 66341 | Q8: 257559 | R8: 370674 | S8: 179321 | T8: 212582 | U8: 1.74 | V8: 17 | W8: 14 | X8: 216304680 | Y8: EU | Z8: 3187920 | AA8: 5471160 | AB8: 8788320 | AC8: 818520 | AD8: 5815800 | AF8: 2972520 | AG8: 2714040 | AH8: 10770000 | AI8: 26106480 | AJ8: 4221840 | AK8: 15250320 | AL8: 1163160 | AM8: 4954200 | AN8: 0 | AO8: 25331040 | AP8: 0 | AQ8: 26278800 | AR8: 0 | AS8: 861600 | AT8: 0 | AU8: 646200 | AV8: 43295400 | AW8: 301560 | AX8: 9348360 | AY8: 1809360 | BA8: 5428080 | BB8: 4264920 | BC8: 2283240 | BD8: 1378560 | BE8: 2843280
A9: 44908 | B9: 44908.46 | C9: Auction 4. Period CAP3 EU | D9: T3PA | E9: successful | F9: 89.01 | G9: 45 | H9: 95 | I9: 88.13 | J9: 89.02 | K9: 2510500 | L9: 4993500 | M9: 82 | N9: 42 | O9: 4.56 | P9: 60896 | Q9: 277417 | R9: 360612 | S9: 179321 | T9: 214991 | U9: 1.99 | V9: 18 | W9: 14 | X9: 223459605 | Y9: EU | Z9: 3293370 | AA9: 5652135 | AB9: 9079020 | AC9: 845595 | AD9: 6008175 | AF9: 3070845 | AG9: 2803815 | AH9: 11126250 | AI9: 26970030 | AJ9: 4361490 | AK9: 15754770 | AL9: 1201635 | AM9: 5118075 | AN9: 0 | AO9: 26168940 | AP9: 0 | AQ9: 27148050 | AR9: 0 | AS9: 890100 | AT9: 0 | AU9: 667575 | AV9: 44727525 | AW9: 311535 | AX9: 9657585 | AY9: 1869210 | BA9: 5607630 | BB9: 4405995 | BC9: 2358765 | BD9: 1424160 | BE9: 2937330
A10: 44907 | B10: 44907.459 | C10: Auction 4. Period CAP3 EU | D10: T3PA | E10: successful | F10: 88.35 | G10: 65 | H10: 95 | I10: 87.7 | J10: 87.99 | K10: 2510500 | L10: 5522500 | M10: 104 | N10: 39 | O10: 4.95 | P10: 53101 | Q10: 262976 | R10: 365700 | S10: 167367 | T10: 225472 | U10: 2.2 | V10: 21 | W10: 15 | X10: 221802675 | Y10: EU | Z10: 3268950 | AA10: 5610225 | AB10: 9011700 | AC10: 839325 | AD10: 5963625 | AF10: 3048075 | AG10: 2783025 | AH10: 11043750 | AI10: 26770050 | AJ10: 4329150 | AK10: 15637950 | AL10: 1192725 | AM10: 5080125 | AN10: 0 | AO10: 25974900 | AP10: 0 | AQ10: 26946750 | AR10: 0 | AS10: 883500 | AT10: 0 | AU10: 662625 | AV10: 44395875 | AW10: 309225 | AX10: 9585975 | AY10: 1855350 | BA10: 5566050 | BB10: 4373325 | BC10: 2341275 | BD10: 1413600 | BE10: 2915550
A11: 44904 | B11: 44904.459 | C11: Auction 4. Period DE | D11: T3PA | E11: successful | F11: 88.26 | G11: 45 | H11: 96 | I11: 87.14 | J11: 88.21 | K11: 1861500 | L11: 4285000 | M11: 76 | N11: 36 | O11: 4.47 | P11: 56382 | Q11: 252059 | R11: 386495 | S11: 132964 | T11: 262744 | U11: 2.3 | V11: 17 | W11: 14 | X11: 164295990 | Y11: DE | AE11: 164295990
A12: 44903 | B12: 44903.459 | C12: Auction 4. Period CAP3 EU | D12: T3PA | E12: successful | F12: 87.91 | G12: 45 | H12: 92 | I12: 86.72 | J12: 87.51 | K12: 2510500 | L12: 4895000 | M12: 92 | N12: 33 | O12: 4.6 | P12: 53207 | Q12: 244750 | R12: 360524 | S12: 167367 | T12: 219384 | U12: 1.95 | V12: 20 | W12: 15 | X12: 220698055 | Y12: EU | Z12: 3252670 | AA12: 5582285 | AB12: 8966820 | AC12: 835145 | AD12: 5933925 | AF12: 3032895 | AG12: 2769165 | AH12: 10988750 | AI12: 26636730 | AJ12: 4307590 | AK12: 15560070 | AL12: 1186785 | AM12: 5054825 | AN12: 0 | AO12: 25845540 | AP12: 0 | AQ12: 26812550 | AR12: 0 | AS12: 879100 | AT12: 0 | AU12: 659325 | AV12: 44174775 | AW12: 307685 | AX12: 9538235 | AY12: 1846110 | BA12: 5538330 | BB12: 4351545 | BC12: 2329615 | BD12: 1406560 | BE12: 2901030
A13: 44902 | B13: 44902.459 | C13: Auction 4. Period CAP3 PL | D13: T3PA | E13: successful | F13: 87 | G13: 70 | H13: 90 | I13: 87.46 | J13: 87.98 | K13: 3102500 | L13: 3691000 | M13: 72 | N13: 60 | O13: 3.79 | P13: 51264 | Q13: 194263 | R13: 296921 | S13: 172361 | T13: 299141 | U13: 1.19 | V13: 19 | W13: 18 | X13: 269917500 | Y13: PL | AZ13: 269917500
A14: 44901 | B14: 44901.459 | C14: Auction 4. Period CAP3 EU | D14: T3PA | E14: successful | F14: 86.48 | G14: 45 | H14: 89 | I14: 85.5 | J14: 86.34 | K14: 2510500 | L14: 5577500 | M14: 65 | N14: 29 | O14: 3.61 | P14: 85808 | Q14: 309861 | R14: 612950 | S14: 156906 | T14: 307654 | U14: 2.22 | V14: 18 | W14: 16 | X14: 217108040 | Y14: EU | Z14: 3199760 | AA14: 5491480 | AB14: 8820960 | AC14: 821560 | AD14: 5837400 | AF14: 2983560 | AG14: 2724120 | AH14: 10810000 | AI14: 26203440 | AJ14: 4237520 | AK14: 15306960 | AL14: 1167480 | AM14: 4972600 | AN14: 0 | AO14: 25425120 | AP14: 0 | AQ14: 26376400 | AR14: 0 | AS14: 864800 | AT14: 0 | AU14: 648600 | AV14: 43456200 | AW14: 302680 | AX14: 9383080 | AY14: 1816080 | BA14: 5448240 | BB14: 4280760 | BC14: 2291720 | BD14: 1383680 | BE14: 2853840
A15: 44900 | B15: 44900.459 | C15: Auction 4. Period CAP3 EU | D15: T3PA | E15: successful | F15: 85.69 | G15: 45 | H15: 88 | I15: 84.65 | J15: 85.56 | K15: 2510500 | L15: 5270000 | M15: 76 | N15: 32 | O15: 3.8 | P15: 69342 | Q15: 263500 | R15: 403820 | S15: 167367 | T15: 308706 | U15: 2.1 | V15: 20 | W15: 15 | X15: 215124745 | Y15: EU | Z15: 3170530 | AA15: 5441315 | AB15: 8740380 | AC15: 814055 | AD15: 5784075 | AF15: 2956305 | AG15: 2699235 | AH15: 10711250 | AI15: 25964070 | AJ15: 4198810 | AK15: 15167130 | AL15: 1156815 | AM15: 4927175 | AN15: 0 | AO15: 25192860 | AP15: 0 | AQ15: 26135450 | AR15: 0 | AS15: 856900 | AT15: 0 | AU15: 642675 | AV15: 43059225 | AW15: 299915 | AX15: 9297365 | AY15: 1799490 | BA15: 5398470 | BB15: 4241655 | BC15: 2270785 | BD15: 1371040 | BE15: 2827770
A16: 44897 | B16: 44897.459 | C16: Auction 4. Period DE | D16: T3PA | E16: successful | F16: 85.21 | G16: 45 | H16: 88.07 | I16: 84.23 | J16: 85.21 | K16: 1861500 | L16: 4229000 | M16: 69 | N16: 35 | O16: 3.63 | P16: 61290 | Q16: 222579 | R16: 358404 | S16: 132964 | T16: 215757 | U16: 2.27 | V16: 19 | W16: 14 | X16: 158618415 | Y16: DE | AE16: 158618415
A17: 44896 | B17: 44896.459 | C17: Auction 4. Period CAP3 EU | D17: T3PA | E17: successful | F17: 86.11 | G17: 45 | H17: 95 | I17: 85.06 | J17: 86.25 | K17: 2510500 | L17: 5094000 | M17: 73 | N17: 40 | O17: 3.48 | P17: 69781 | Q17: 242571 | R17: 347570 | S17: 147676 | T17: 209970 | U17: 2.03 | V17: 21 | W17: 17 | X17: 216179155 | Y17: EU | Z17: 3186070 | AA17: 5467985 | AB17: 8783220 | AC17: 818045 | AD17: 5812425 | AF17: 2970795 | AG17: 2712465 | AH17: 10763750 | AI17: 26091330 | AJ17: 4219390 | AK17: 15241470 | AL17: 1162485 | AM17: 4951325 | AN17: 0 | AO17: 25316340 | AP17: 0 | AQ17: 26263550 | AR17: 0 | AS17: 861100 | AT17: 0 | AU17: 645825 | AV17: 43270275 | AW17: 301385 | AX17: 9342935 | AY17: 1808310 | BA17: 5424930 | BB17: 4262445 | BC17: 2281915 | BD17: 1377760 | BE17: 2841630
A18: 44894 | B18: 44894.459 | C18: Auction 4. Period CAP3 EU | D18: T3PA | E18: successful | F18: 78.88 | G18: 60 | H18: 88 | I18: 78.42 | J18: 78.48 | K18: 2510500 | L18: 5626000 | M18: 94 | N18: 31 | O18: 4.27 | P18: 59851 | Q18: 255727 | R18: 344183 | S18: 167367 | T18: 204599 | U18: 2.24 | V18: 22 | W18: 15 | X18: 198028240 | Y18: EU | Z18: 2918560 | AA18: 5008880 | AB18: 8045760 | AC18: 749360 | AD18: 5324400 | AF18: 2721360 | AG18: 2484720 | AH18: 9860000 | AI18: 23900640 | AJ18: 3865120 | AK18: 13961760 | AL18: 1064880 | AM18: 4535600 | AN18: 0 | AO18: 23190720 | AP18: 0 | AQ18: 24058400 | AR18: 0 | AS18: 788800 | AT18: 0 | AU18: 591600 | AV18: 39637200 | AW18: 276080 | AX18: 8558480 | AY18: 1656480 | BA18: 4969440 | BB18: 3904560 | BC18: 2090320 | BD18: 1262080 | BE18: 2603040
A19: 44893 | B19: 44893.459 | C19: Auction 4. Period CAP3 EU | D19: T3PA | E19: successful | F19: 77.61 | G19: 45 | H19: 81 | I19: 76.8 | J19: 77.39 | K19: 2510500 | L19: 5072000 | M19: 65 | N19: 25 | O19: 3.61 | P19: 78031 | Q19: 281778 | R19: 385424 | S19: 209208 | T19: 257757 | U19: 2.02 | V19: 18 | W19: 12 | X19: 194839905 | Y19: EU | Z19: 2871570 | AA19: 4928235 | AB19: 7916220 | AC19: 737295 | AD19: 5238675 | AF19: 2677545 | AG19: 2444715 | AH19: 9701250 | AI19: 23515830 | AJ19: 3802890 | AK19: 13736970 | AL19: 1047735 | AM19: 4462575 | AN19: 0 | AO19: 22817340 | AP19: 0 | AQ19: 23671050 | AR19: 0 | AS19: 776100 | AT19: 0 | AU19: 582075 | AV19: 38999025 | AW19: 271635 | AX19: 8420685 | AY19: 1629810 | BA19: 4889430 | BB19: 3841695 | BC19: 2056665 | BD19: 1241760 | BE19: 2561130
A20: 44890 | B20: 44890.459 | C20: Auction 4. Period DE | D20: T3PA | E20: successful | F20: 79.36 | G20: 45 | H20: 82 | I20: 78.56 | J20: 79.11 | K20: 1861500 | L20: 3688000 | M20: 61 | N20: 23 | O20: 3.21 | P20: 60459 | Q20: 194105 | R20: 367077 | S20: 124100 | T20: 241286 | U20: 1.98 | V20: 19 | W20: 15 | X20: 147728640 | Y20: DE | AE20: 147728640
A21: 44889 | B21: 44889.459 | C21: Auction 4. Period CAP3 EU | D21: T3PA | E21: successful | F21: 76.64 | G21: 45 | H21: 84 | I21: 76.05 | J21: 76.19 | K21: 2510500 | L21: 5707000 | M21: 83 | N21: 26 | O21: 4.15 | P21: 68759 | Q21: 285350 | R21: 385430 | S21: 228227 | T21: 256325 | U21: 2.27 | V21: 20 | W21: 11 | X21: 192404720 | Y21: EU | Z21: 2835680 | AA21: 4866640 | AB21: 7817280 | AC21: 728080 | AD21: 5173200 | AF21: 2644080 | AG21: 2414160 | AH21: 9580000 | AI21: 23221920 | AJ21: 3755360 | AK21: 13565280 | AL21: 1034640 | AM21: 4406800 | AN21: 0 | AO21: 22532160 | AP21: 0 | AQ21: 23375200 | AR21: 0 | AS21: 766400 | AT21: 0 | AU21: 574800 | AV21: 38511600 | AW21: 268240 | AX21: 8315440 | AY21: 1609440 | BA21: 4828320 | BB21: 3793680 | BC21: 2030960 | BD21: 1226240 | BE21: 2529120
A22: 44888 | B22: 44888.459 | C22: Auction 4. Period CAP3 PL | D22: T3PA | E22: successful | F22: 74.08 | G22: 45 | H22: 86 | I22: 74.44 | J22: 73.9 | K22: 3101500 | L22: 7498500 | M22: 79 | N22: 34 | O22: 3.95 | P22: 94918 | Q22: 374925 | R22: 775599 | S22: 221536 | T22: 323935 | U22: 2.42 | V22: 20 | W22: 14 | X22: 229759120 | Y22: PL | AZ22: 229759120
A23: 44887 | B23: 44887.459 | C23: Auction 4. Period CAP3 EU | D23: T3PA | E23: successful | F23: 73.54 | G23: 45 | H23: 77.6 | I23: 72.93 | J23: 73.26 | K23: 2510500 | L23: 5360500 | M23: 76 | N23: 29 | O23: 3.8 | P23: 70533 | Q23: 268025 | R23: 380852 | S23: 167367 | T23: 242173 | U23: 2.14 | V23: 20 | W23: 15 | X23: 184622170 | Y23: EU | Z23: 2720980 | AA23: 4669790 | AB23: 7501080 | AC23: 698630 | AD23: 4963950 | AF23: 2537130 | AG23: 2316510 | AH23: 9192500 | AI23: 22282620 | AJ23: 3603460 | AK23: 13016580 | AL23: 992790 | AM23: 4228550 | AN23: 0 | AO23: 21620760 | AP23: 0 | AQ23: 22429700 | AR23: 0 | AS23: 735400 | AT23: 0 | AU23: 551550 | AV23: 36953850 | AW23: 257390 | AX23: 7979090 | AY23: 1544340 | BA23: 4633020 | BB23: 3640230 | BC23: 1948810 | BD23: 1176640 | BE23: 2426820
A24: 44886 | B24: 44886.459 | C24: Auction 4. Period CAP3 EU | D24: T3PA | E24: successful | F24: 73.36 | G24: 45 | H24: 75.9 | I24: 72.73 | J24: 73.16 | K24: 2510500 | L24: 5503000 | M24: 85 | N24: 32 | O24: 3.86 | P24: 64741 | Q24: 250136 | R24: 403422 | S24: 167367 | T24: 315875 | U24: 2.19 | V24: 22 | W24: 15 | X24: 184170280 | Y24: EU | Z24: 2714320 | AA24: 4658360 | AB24: 7482720 | AC24: 696920 | AD24: 4951800 | AF24: 2530920 | AG24: 2310840 | AH24: 9170000 | AI24: 22228080 | AJ24: 3594640 | AK24: 12984720 | AL24: 990360 | AM24: 4218200 | AN24: 0 | AO24: 21567840 | AP24: 0 | AQ24: 22374800 | AR24: 0 | AS24: 733600 | AT24: 0 | AU24: 550200 | AV24: 36863400 | AW24: 256760 | AX24: 7959560 | AY24: 1540560 | BA24: 4621680 | BB24: 3631320 | BC24: 1944040 | BD24: 1173760 | BE24: 2420880
A25: 44883 | B25: 44883.459 | C25: Auction 4. Period DE | D25: T3PA | E25: successful | F25: 72.22 | G25: 60 | H25: 76 | I25: 71.85 | J25: 72.22 | K25: 1861500 | L25: 4667000 | M25: 65 | N25: 33 | O25: 3.61 | P25: 71800 | Q25: 259278 | R25: 452179 | S25: 116344 | T25: 283459 | U25: 2.51 | V25: 18 | W25: 16 | X25: 134437530 | Y25: DE | AE25: 134437530
A26: 44882 | B26: 44882.459 | C26: Auction 4. Period CAP3 EU | D26: T3PA | E26: successful | F26: 73.31 | G26: 45 | H26: 79 | I26: 73.37 | J26: 73.71 | K26: 2510500 | L26: 4054500 | M26: 65 | N26: 50 | O26: 3.82 | P26: 62377 | Q26: 238500 | R26: 410980 | S26: 147676 | T26: 265935 | U26: 1.62 | V26: 17 | W26: 17 | X26: 184044755 | Y26: EU | Z26: 2712470 | AA26: 4655185 | AB26: 7477620 | AC26: 696445 | AD26: 4948425 | AF26: 2529195 | AG26: 2309265 | AH26: 9163750 | AI26: 22212930 | AJ26: 3592190 | AK26: 12975870 | AL26: 989685 | AM26: 4215325 | AN26: 0 | AO26: 21553140 | AP26: 0 | AQ26: 22359550 | AR26: 0 | AS26: 733100 | AT26: 0 | AU26: 549825 | AV26: 36838275 | AW26: 256585 | AX26: 7954135 | AY26: 1539510 | BA26: 4618530 | BB26: 3628845 | BC26: 1942715 | BD26: 1172960 | BE26: 2419230
A27: 44881 | B27: 44881.459 | C27: EUAA Auction CAP3 EU | D27: EAA3 | E27: successful | F27: 74.25 | G27: 72.5 | H27: 75.23 | I27: 74.34 | J27: 74.36 | K27: 602000 | L27: 954000 | M27: 35 | N27: 21 | O27: 5 | P27: 27257 | Q27: 136286 | R27: 195404 | S27: 120400 | T27: 127820 | U27: 1.58 | V27: 7 | W27: 5 | X27: 44698500 | Y27: EU | Z27: 1225125 | AA27: 1522125 | AB27: 556875 | AC27: 445500 | AD27: 556875 | AF27: 1485000 | AG27: 111375 | AH27: 2895750 | AI27: 8241750 | AJ27: 1113750 | AK27: 6199875 | AL27: 482625 | AM27: 594000 | AN27: 1002375 | AP27: 445500 | AQ27: 6756750 | AR27: 0 | AS27: 185625 | AT27: 222750 | AU27: 297000 | AW27: 297000 | AX27: 2413125 | AY27: 2376000 | BA27: 2079000 | BB27: 965250 | BC27: 2041875 | BD27: 37125 | BE27: 148500
A28: 44880 | B28: 44880.459 | C28: Auction 4. Period CAP3 EU | D28: T3PA | E28: successful | F28: 74.93 | G28: 45 | H28: 79 | I28: 74.76 | J28: 75.12 | K28: 2510500 | L28: 4354000 | M28: 69 | N28: 44 | O28: 4.06 | P28: 63101 | Q28: 256118 | R28: 388914 | S28: 167367 | T28: 259294 | U28: 1.73 | V28: 17 | W28: 15 | X28: 188111765 | Y28: EU | Z28: 2772410 | AA28: 4758055 | AB28: 7642860 | AC28: 711835 | AD28: 5057775 | AF28: 2585085 | AG28: 2360295 | AH28: 9366250 | AI28: 22703790 | AJ28: 3671570 | AK28: 13262610 | AL28: 1011555 | AM28: 4308475 | AN28: 0 | AO28: 22029420 | AP28: 0 | AQ28: 22853650 | AR28: 0 | AS28: 749300 | AT28: 0 | AU28: 561975 | AV28: 37652325 | AW28: 262255 | AX28: 8129905 | AY28: 1573530 | BA28: 4720590 | BB28: 3709035 | BC28: 1985645 | BD28: 1198880 | BE28: 2472690
A29: 44879 | B29: 44879.459 | C29: Auction 4. Period CAP3 EU | D29: T3PA | E29: successful | F29: 74.85 | G29: 67.48 | H29: 77.3 | I29: 74.69 | J29: 74.65 | K29: 2510500 | L29: 4926000 | M29: 79 | N29: 29 | O29: 3.95 | P29: 62354 | Q29: 246300 | R29: 423501 | S29: 167367 | T29: 333330 | U29: 1.96 | V29: 20 | W29: 15 | X29: 187910925 | Y29: EU | Z29: 2769450 | AA29: 4752975 | AB29: 7634700 | AC29: 711075 | AD29: 5052375 | AF29: 2582325 | AG29: 2357775 | AH29: 9356250 | AI29: 22679550 | AJ29: 3667650 | AK29: 13248450 | AL29: 1010475 | AM29: 4303875 | AN29: 0 | AO29: 22005900 | AP29: 0 | AQ29: 22829250 | AR29: 0 | AS29: 748500 | AT29: 0 | AU29: 561375 | AV29: 37612125 | AW29: 261975 | AX29: 8121225 | AY29: 1571850 | BA29: 4715550 | BB29: 3705075 | BC29: 1983525 | BD29: 1197600 | BE29: 2470050
A30: 44876 | B30: 44876.459 | C30: Auction 4. Period DE | D30: T3PA | E30: successful | F30: 73.33 | G30: 60 | H30: 75.75 | I30: 73.1 | J30: 73.29 | K30: 1861500 | L30: 4295000 | M30: 71 | N30: 35 | O30: 3.74 | P30: 60493 | Q30: 226053 | R30: 331727 | S30: 116344 | T30: 145222 | U30: 2.31 | V30: 19 | W30: 16 | X30: 136503795 | Y30: DE | AE30: 136503795
A31: 44875 | B31: 44875.459 | C31: Auction 4. Period CAP3 EU | D31: T3PA | E31: successful | F31: 71.62 | G31: 60 | H31: 77 | I31: 70.74 | J31: 70.7 | K31: 2510500 | L31: 5622000 | M31: 74 | N31: 14 | O31: 3.52 | P31: 75973 | Q31: 267714 | R31: 436486 | S31: 313813 | T31: 425868 | U31: 2.24 | V31: 21 | W31: 8 | X31: 179802010 | Y31: EU | Z31: 2649940 | AA31: 4547870 | AB31: 7305240 | AC31: 680390 | AD31: 4834350 | AF31: 2470890 | AG31: 2256030 | AH31: 8952500 | AI31: 21700860 | AJ31: 3509380 | AK31: 12676740 | AL31: 966870 | AM31: 4118150 | AN31: 0 | AO31: 21056280 | AP31: 0 | AQ31: 21844100 | AR31: 0 | AS31: 716200 | AT31: 0 | AU31: 537150 | AV31: 35989050 | AW31: 250670 | AX31: 7770770 | AY31: 1504020 | BA31: 4512060 | BB31: 3545190 | BC31: 1897930 | BD31: 1145920 | BE31: 2363460
A32: 44874 | B32: 44874.459 | C32: Auction 4. Period CAP3 PL | D32: T3PA | E32: successful | F32: 75.35 | G32: 68.02 | H32: 80 | I32: 75.53 | J32: 75.35 | K32: 3101500 | L32: 5108000 | M32: 76 | N32: 39 | O32: 4.47 | P32: 67211 | Q32: 300471 | R32: 468830 | S32: 206767 | T32: 361064 | U32: 1.65 | V32: 17 | W32: 15 | X32: 233698025 | Y32: PL | AZ32: 233698025
A33: 44873 | B33: 44873.459 | C33: Auction 4. Period CAP3 EU | D33: T3PA | E33: successful | F33: 76.02 | G33: 60 | H33: 80 | I33: 76.01 | J33: 76.13 | K33: 2510500 | L33: 4924000 | M33: 72 | N33: 41 | O33: 3.6 | P33: 68389 | Q33: 246200 | R33: 372981 | S33: 147676 | T33: 241130 | U33: 1.96 | V33: 20 | W33: 17 | X33: 190848210 | Y33: EU | Z33: 2812740 | AA33: 4827270 | AB33: 7754040 | AC33: 722190 | AD33: 5131350 | AF33: 2622690 | AG33: 2394630 | AH33: 9502500 | AI33: 23034060 | AJ33: 3724980 | AK33: 13455540 | AL33: 1026270 | AM33: 4371150 | AN33: 0 | AO33: 22349880 | AP33: 0 | AQ33: 23186100 | AR33: 0 | AS33: 760200 | AT33: 0 | AU33: 570150 | AV33: 38200050 | AW33: 266070 | AX33: 8248170 | AY33: 1596420 | BA33: 4789260 | BB33: 3762990 | BC33: 2014530 | BD33: 1216320 | BE33: 2508660
A34: 44872 | B34: 44872.46 | C34: Auction 4. Period CAP3 EU | D34: T3PA | E34: successful | F34: 76.75 | G34: 60 | H34: 79 | I34: 76.09 | J34: 76.28 | K34: 2510500 | L34: 6263500 | M34: 88 | N34: 23 | O34: 4.19 | P34: 71176 | Q34: 298262 | R34: 539582 | S34: 228227 | T34: 255269 | U34: 2.49 | V34: 21 | W34: 11 | X34: 192680875 | Y34: EU | Z34: 2839750 | AA34: 4873625 | AB34: 7828500 | AC34: 729125 | AD34: 5180625 | AF34: 2647875 | AG34: 2417625 | AH34: 9593750 | AI34: 23255250 | AJ34: 3760750 | AK34: 13584750 | AL34: 1036125 | AM34: 4413125 | AN34: 0 | AO34: 22564500 | AP34: 0 | AQ34: 23408750 | AR34: 0 | AS34: 767500 | AT34: 0 | AU34: 575625 | AV34: 38566875 | AW34: 268625 | AX34: 8327375 | AY34: 1611750 | BA34: 4835250 | BB34: 3799125 | BC34: 2033875 | BD34: 1228000 | BE34: 2532750
A35: 44869 | B35: 44869.459 | C35: Auction 4. Period DE | D35: T3PA | E35: successful | F35: 78.14 | G35: 60 | H35: 80.05 | I35: 77.17 | J35: 77.35 | K35: 1861500 | L35: 4360000 | M35: 71 | N35: 14 | O35: 3.55 | P35: 61408 | Q35: 218000 | R35: 340984 | S35: 232688 | T35: 234939 | U35: 2.34 | V35: 20 | W35: 8 | X35: 145457610 | Y35: DE | AE35: 145457610
A36: 44868 | B36: 44868.459 | C36: Auction 4. Period CAP3 EU | D36: T3PA | E36: successful | F36: 76.63 | G36: 45 | H36: 79 | I36: 75.49 | J36: 76.08 | K36: 2510500 | L36: 4429000 | M36: 68 | N36: 15 | O36: 3.58 | P36: 65132 | Q36: 233105 | R36: 271143 | S36: 278944 | T36: 252110 | U36: 1.76 | V36: 19 | W36: 9 | X36: 192379615 | Y36: EU | Z36: 2835310 | AA36: 4866005 | AB36: 7816260 | AC36: 727985 | AD36: 5172525 | AF36: 2643735 | AG36: 2413845 | AH36: 9578750 | AI36: 23218890 | AJ36: 3754870 | AK36: 13563510 | AL36: 1034505 | AM36: 4406225 | AN36: 0 | AO36: 22529220 | AP36: 0 | AQ36: 23372150 | AR36: 0 | AS36: 766300 | AT36: 0 | AU36: 574725 | AV36: 38506575 | AW36: 268205 | AX36: 8314355 | AY36: 1609230 | BA36: 4827690 | BB36: 3793185 | BC36: 2030695 | BD36: 1226080 | BE36: 2528790
A37: 44866 | B37: 44866.459 | C37: Auction 4. Period CAP3 EU | D37: T3PA | E37: successful | F37: 78.76 | G37: 45 | H37: 82 | I37: 78.46 | J37: 78.88 | K37: 2510500 | L37: 4376500 | M37: 63 | N37: 37 | O37: 3.71 | P37: 69468 | Q37: 257441 | R37: 373441 | S37: 147676 | T37: 217253 | U37: 1.74 | V37: 17 | W37: 17 | X37: 197726980 | Y37: EU | Z37: 2914120 | AA37: 5001260 | AB37: 8033520 | AC37: 748220 | AD37: 5316300 | AF37: 2717220 | AG37: 2480940 | AH37: 9845000 | AI37: 23864280 | AJ37: 3859240 | AK37: 13940520 | AL37: 1063260 | AM37: 4528700 | AN37: 0 | AO37: 23155440 | AP37: 0 | AQ37: 24021800 | AR37: 0 | AS37: 787600 | AT37: 0 | AU37: 590700 | AV37: 39576900 | AW37: 275660 | AX37: 8545460 | AY37: 1653960 | BA37: 4961880 | BB37: 3898620 | BC37: 2087140 | BD37: 1260160 | BE37: 2599080
A38: 44865 | B38: 44865.46 | C38: Auction 4. Period CAP3 EU | D38: T3PA | E38: successful | F38: 78.69 | G38: 45 | H38: 85 | I38: 77.89 | J38: 78.57 | K38: 2510500 | L38: 6271500 | M38: 64 | N38: 29 | O38: 3.76 | P38: 97992 | Q38: 368912 | R38: 745631 | S38: 209208 | T38: 284809 | U38: 2.5 | V38: 17 | W38: 12 | X38: 197551245 | Y38: EU | Z38: 2911530 | AA38: 4996815 | AB38: 8026380 | AC38: 747555 | AD38: 5311575 | AF38: 2714805 | AG38: 2478735 | AH38: 9836250 | AI38: 23843070 | AJ38: 3855810 | AK38: 13928130 | AL38: 1062315 | AM38: 4524675 | AN38: 0 | AO38: 23134860 | AP38: 0 | AQ38: 24000450 | AR38: 0 | AS38: 786900 | AT38: 0 | AU38: 590175 | AV38: 39541725 | AW38: 275415 | AX38: 8537865 | AY38: 1652490 | BA38: 4957470 | BB38: 3895155 | BC38: 2085285 | BD38: 1259040 | BE38: 2596770
A39: 44862 | B39: 44862.459 | C39: Auction 4. Period DE | D39: T3PA | E39: successful | F39: 80.76 | G39: 45 | H39: 88 | I39: 80.73 | J39: 81.14 | K39: 1861500 | L39: 4441000 | M39: 64 | N39: 47 | O39: 3.56 | P39: 69391 | Q39: 246722 | R39: 443497 | S39: 109500 | T39: 158299 | U39: 2.39 | V39: 18 | W39: 17 | X39: 150334740 | Y39: DE | AE39: 150334740
A40: 44861 | B40: 44861.459 | C40: Auction 4. Period CAP3 EU | D40: T3PA | E40: successful | F40: 77.1 | G40: 45 | H40: 82 | I40: 76.32 | J40: 76.56 | K40: 2510500 | L40: 4882000 | M40: 78 | N40: 25 | O40: 4.33 | P40: 62590 | Q40: 271222 | R40: 390819 | S40: 228227 | T40: 268231 | U40: 1.94 | V40: 18 | W40: 11 | X40: 193559550 | Y40: EU | Z40: 2852700 | AA40: 4895850 | AB40: 7864200 | AC40: 732450 | AD40: 5204250 | AF40: 2659950 | AG40: 2428650 | AH40: 9637500 | AI40: 23361300 | AJ40: 3777900 | AK40: 13646700 | AL40: 1040850 | AM40: 4433250 | AN40: 0 | AO40: 22667400 | AP40: 0 | AQ40: 23515500 | AR40: 0 | AS40: 771000 | AT40: 0 | AU40: 578250 | AV40: 38742750 | AW40: 269850 | AX40: 8365350 | AY40: 1619100 | BA40: 4857300 | BB40: 3816450 | BC40: 2043150 | BD40: 1233600 | BE40: 2544300
A41: 44860 | B41: 44860.459 | C41: Auction 4. Period CAP3 PL | D41: T3PA | E41: successful | F41: 76.51 | G41: 45 | H41: 80 | I41: 75.78 | J41: 76.31 | K41: 3101500 | L41: 7930500 | M41: 91 | N41: 35 | O41: 4.33 | P41: 87148 | Q41: 377643 | R41: 761956 | S41: 221536 | T41: 348642 | U41: 2.56 | V41: 21 | W41: 14 | X41: 237295765 | Y41: PL | AZ41: 237295765
A42: 44859 | B42: 44859.459 | C42: Auction 4. Period CAP3 EU | D42: T3PA | E42: successful | F42: 74.17 | G42: 60 | H42: 82 | I42: 74.06 | J42: 74.01 | K42: 2510500 | L42: 5010500 | M42: 64 | N42: 27 | O42: 4 | P42: 78289 | Q42: 313156 | R42: 438447 | S42: 209208 | T42: 322153 | U42: 2 | V42: 16 | W42: 12 | X42: 186203785 | Y42: EU | Z42: 2744290 | AA42: 4709795 | AB42: 7565340 | AC42: 704615 | AD42: 5006475 | AF42: 2558865 | AG42: 2336355 | AH42: 9271250 | AI42: 22473510 | AJ42: 3634330 | AK42: 13128090 | AL42: 1001295 | AM42: 4264775 | AN42: 0 | AO42: 21805980 | AP42: 0 | AQ42: 22621850 | AR42: 0 | AS42: 741700 | AT42: 0 | AU42: 556275 | AV42: 37270425 | AW42: 259595 | AX42: 8047445 | AY42: 1557570 | BA42: 4672710 | BB42: 3671415 | BC42: 1965505 | BD42: 1186720 | BE42: 2447610
A43: 44858 | B43: 44858.459 | C43: Auction 4. Period CAP3 EU | D43: T3PA | E43: successful | F43: 68.02 | G43: 60 | H43: 75 | I43: 67.72 | J43: 67.55 | K43: 2510500 | L43: 5385500 | M43: 71 | N43: 22 | O43: 3.74 | P43: 75852 | Q43: 283447 | R43: 431640 | S43: 228227 | T43: 343924 | U43: 2.15 | V43: 19 | W43: 11 | X43: 170764210 | Y43: EU | Z43: 2516740 | AA43: 4319270 | AB43: 6938040 | AC43: 646190 | AD43: 4591350 | AF43: 2346690 | AG43: 2142630 | AH43: 8502500 | AI43: 20610060 | AJ43: 3332980 | AK43: 12039540 | AL43: 918270 | AM43: 3911150 | AN43: 0 | AO43: 19997880 | AP43: 0 | AQ43: 20746100 | AR43: 0 | AS43: 680200 | AT43: 0 | AU43: 510150 | AV43: 34180050 | AW43: 238070 | AX43: 7380170 | AY43: 1428420 | BA43: 4285260 | BB43: 3366990 | BC43: 1802530 | BD43: 1088320 | BE43: 2244660
A44: 44855 | B44: 44855.459 | C44: Auction 4. Period DE | D44: T3PA | E44: successful | F44: 67.9 | G44: 60 | H44: 69.9 | I44: 67.43 | J44: 67.51 | K44: 1861500 | L44: 4923500 | M44: 71 | N44: 26 | O44: 4.18 | P44: 69345 | Q44: 289618 | R44: 467946 | S44: 169227 | T44: 227843 | U44: 2.64 | V44: 17 | W44: 11 | X44: 126395850 | Y44: DE | AE44: 126395850
A45: 44854 | B45: 44854.459 | C45: Auction 4. Period CAP3 EU | D45: T3PA | E45: successful | F45: 67.01 | G45: 57 | H45: 75 | I45: 66.49 | J45: 66.53 | K45: 2510500 | L45: 6175500 | M45: 80 | N45: 21 | O45: 4.71 | P45: 77194 | Q45: 363265 | R45: 593651 | S45: 278944 | T45: 384801 | U45: 2.46 | V45: 17 | W45: 9 | X45: 168228605 | Y45: EU | Z45: 2479370 | AA45: 4255135 | AB45: 6835020 | AC45: 636595 | AD45: 4523175 | AF45: 2311845 | AG45: 2110815 | AH45: 8376250 | AI45: 20304030 | AJ45: 3283490 | AK45: 11860770 | AL45: 904635 | AM45: 3853075 | AN45: 0 | AO45: 19700940 | AP45: 0 | AQ45: 20438050 | AR45: 0 | AS45: 670100 | AT45: 0 | AU45: 502575 | AV45: 33672525 | AW45: 234535 | AX45: 7270585 | AY45: 1407210 | BA45: 4221630 | BB45: 3316995 | BC45: 1775765 | BD45: 1072160 | BE45: 2211330
A46: 44853 | B46: 44853.459 | C46: EUAA Auction DE | D46: EAA3 | E46: successful | F46: 68.62 | G46: 67.68 | H46: 70.9 | I46: 68.46 | J46: 68.36 | K46: 586500 | L46: 1178000 | M46: 28 | N46: 9 | O46: 4.67 | P46: 42071 | Q46: 196333 | R46: 189354 | S46: 146625 | T46: 117273 | U46: 2.01 | V46: 6 | W46: 4 | X46: 40245630 | Y46: DE | AE46: 40245630
A47: 44852 | B47: 44852.459 | C47: Auction 4. Period CAP3 EU | D47: T3PA | E47: successful | F47: 67.11 | G47: 56 | H47: 75 | I47: 66.36 | J47: 66.5 | K47: 2510500 | L47: 6788500 | M47: 75 | N47: 19 | O47: 3.75 | P47: 90513 | Q47: 339425 | R47: 466138 | S47: 209208 | T47: 194749 | U47: 2.7 | V47: 20 | W47: 12 | X47: 168479655 | Y47: EU | Z47: 2483070 | AA47: 4261485 | AB47: 6845220 | AC47: 637545 | AD47: 4529925 | AF47: 2315295 | AG47: 2113965 | AH47: 8388750 | AI47: 20334330 | AJ47: 3288390 | AK47: 11878470 | AL47: 905985 | AM47: 3858825 | AN47: 0 | AO47: 19730340 | AP47: 0 | AQ47: 20468550 | AR47: 0 | AS47: 671100 | AT47: 0 | AU47: 503325 | AV47: 33722775 | AW47: 234885 | AX47: 7281435 | AY47: 1409310 | BA47: 4227930 | BB47: 3321945 | BC47: 1778415 | BD47: 1073760 | BE47: 2214630
A48: 44851 | B48: 44851.459 | C48: Auction 4. Period CAP3 EU | D48: T3PA | E48: successful | F48: 66.25 | G48: 57 | H48: 68.6 | I48: 66.1 | J48: 66.32 | K48: 2510500 | L48: 5754000 | M48: 85 | N48: 47 | O48: 4.47 | P48: 67694 | Q48: 302842 | R48: 544157 | S48: 156906 | T48: 226847 | U48: 2.29 | V48: 19 | W48: 16 | X48: 166320625 | Y48: EU | Z48: 2451250 | AA48: 4206875 | AB48: 6757500 | AC48: 629375 | AD48: 4471875 | AF48: 2285625 | AG48: 2086875 | AH48: 8281250 | AI48: 20073750 | AJ48: 3246250 | AK48: 11726250 | AL48: 894375 | AM48: 3809375 | AN48: 0 | AO48: 19477500 | AP48: 0 | AQ48: 20206250 | AR48: 0 | AS48: 662500 | AT48: 0 | AU48: 496875 | AV48: 33290625 | AW48: 231875 | AX48: 7188125 | AY48: 1391250 | BA48: 4173750 | BB48: 3279375 | BC48: 1755625 | BD48: 1060000 | BE48: 2186250
A49: 44848 | B49: 44848.459 | C49: Auction 4. Period DE | D49: T3PA | E49: successful | F49: 67.7 | G49: 50.45 | H49: 75 | I49: 67.22 | J49: 67.63 | K49: 1861500 | L49: 5928500 | M49: 67 | N49: 30 | O49: 4.47 | P49: 88485 | Q49: 395233 | R49: 613339 | S49: 143192 | T49: 206430 | U49: 3.18 | V49: 15 | W49: 13 | X49: 126023550 | Y49: DE | AE49: 126023550
A50: 44847 | B50: 44847.459 | C50: Auction 4. Period CAP3 EU | D50: T3PA | E50: successful | F50: 66.65 | G50: 51.15 | H50: 80 | I50: 66.54 | J50: 66.43 | K50: 2510500 | L50: 6003500 | M50: 64 | N50: 25 | O50: 4.27 | P50: 93805 | Q50: 400233 | R50: 644127 | S50: 209208 | T50: 304321 | U50: 2.39 | V50: 15 | W50: 12 | X50: 167324825 | Y50: EU | Z50: 2466050 | AA50: 4232275 | AB50: 6798300 | AC50: 633175 | AD50: 4498875 | AF50: 2299425 | AG50: 2099475 | AH50: 8331250 | AI50: 20194950 | AJ50: 3265850 | AK50: 11797050 | AL50: 899775 | AM50: 3832375 | AN50: 0 | AO50: 19595100 | AP50: 0 | AQ50: 20328250 | AR50: 0 | AS50: 666500 | AT50: 0 | AU50: 499875 | AV50: 33491625 | AW50: 233275 | AX50: 7231525 | AY50: 1399650 | BA50: 4198950 | BB50: 3299175 | BC50: 1766225 | BD50: 1066400 | BE50: 2199450
A51: 44846 | B51: 44846.459 | C51: Auction 4. Period CAP3 PL | D51: T3PA | E51: successful | F51: 65.76 | G51: 51 | H51: 72 | I51: 65.86 | J51: 65.7 | K51: 3101500 | L51: 7662500 | M51: 101 | N51: 46 | O51: 5.61 | P51: 75866 | Q51: 425694 | R51: 681887 | S51: 221536 | T51: 282685 | U51: 2.47 | V51: 18 | W51: 14 | X51: 203954640 | Y51: PL | AZ51: 203954640
A52: 44845 | B52: 44845.459 | C52: Auction 4. Period CAP3 EU | D52: T3PA | E52: successful | F52: 66.34 | G52: 59.35 | H52: 70 | I52: 65.86 | J52: 65.83 | K52: 2510500 | L52: 5030500 | M52: 68 | N52: 17 | O52: 4 | P52: 73978 | Q52: 295912 | R52: 350520 | S52: 251050 | T52: 290359 | U52: 2 | V52: 17 | W52: 10 | X52: 166546570 | Y52: EU | Z52: 2454580 | AA52: 4212590 | AB52: 6766680 | AC52: 630230 | AD52: 4477950 | AF52: 2288730 | AG52: 2089710 | AH52: 8292500 | AI52: 20101020 | AJ52: 3250660 | AK52: 11742180 | AL52: 895590 | AM52: 3814550 | AN52: 0 | AO52: 19503960 | AP52: 0 | AQ52: 20233700 | AR52: 0 | AS52: 663400 | AT52: 0 | AU52: 497550 | AV52: 33335850 | AW52: 232190 | AX52: 7197890 | AY52: 1393140 | BA52: 4179420 | BB52: 3283830 | BC52: 1758010 | BD52: 1061440 | BE52: 2189220
A53: 44844 | B53: 44844.459 | C53: Auction 4. Period CAP3 EU | D53: T3PA | E53: successful | F53: 67.01 | G53: 60.12 | H53: 75 | I53: 66.62 | J53: 66.51 | K53: 2510500 | L53: 4884000 | M53: 77 | N53: 15 | O53: 4.05 | P53: 63429 | Q53: 257053 | R53: 399926 | S53: 228227 | T53: 414652 | U53: 1.95 | V53: 19 | W53: 11 | X53: 168228605 | Y53: EU | Z53: 2479370 | AA53: 4255135 | AB53: 6835020 | AC53: 636595 | AD53: 4523175 | AF53: 2311845 | AG53: 2110815 | AH53: 8376250 | AI53: 20304030 | AJ53: 3283490 | AK53: 11860770 | AL53: 904635 | AM53: 3853075 | AN53: 0 | AO53: 19700940 | AP53: 0 | AQ53: 20438050 | AR53: 0 | AS53: 670100 | AT53: 0 | AU53: 502575 | AV53: 33672525 | AW53: 234535 | AX53: 7270585 | AY53: 1407210 | BA53: 4221630 | BB53: 3316995 | BC53: 1775765 | BD53: 1072160 | BE53: 2211330
A54: 44841 | B54: 44841.459 | C54: Auction 4. Period DE | D54: T3PA | E54: successful | F54: 67.52 | G54: 60 | H54: 75 | I54: 67.59 | J54: 67.5 | K54: 1861500 | L54: 3768500 | M54: 80 | N54: 38 | O54: 4.21 | P54: 47106 | Q54: 198342 | R54: 284600 | S54: 116344 | T54: 220447 | U54: 2.02 | V54: 19 | W54: 16 | X54: 125688480 | Y54: DE | AE54: 125688480
A55: 44840 | B55: 44840.459 | C55: Auction 4. Period CAP3 EU | D55: T3PA | E55: successful | F55: 65.76 | G55: 55.35 | H55: 70 | I55: 65.35 | J55: 65.54 | K55: 2510500 | L55: 6652500 | M55: 73 | N55: 26 | O55: 3.84 | P55: 91130 | Q55: 350132 | R55: 643859 | S55: 179321 | T55: 338012 | U55: 2.65 | V55: 19 | W55: 14 | X55: 165090480 | Y55: EU | Z55: 2433120 | AA55: 4175760 | AB55: 6707520 | AC55: 624720 | AD55: 4438800 | AF55: 2268720 | AG55: 2071440 | AH55: 8220000 | AI55: 19925280 | AJ55: 3222240 | AK55: 11639520 | AL55: 887760 | AM55: 3781200 | AN55: 0 | AO55: 19333440 | AP55: 0 | AQ55: 20056800 | AR55: 0 | AS55: 657600 | AT55: 0 | AU55: 493200 | AV55: 33044400 | AW55: 230160 | AX55: 7134960 | AY55: 1380960 | BA55: 4142880 | BB55: 3255120 | BC55: 1742640 | BD55: 1052160 | BE55: 2170080
A56: 44838 | B56: 44838.459 | C56: Auction 4. Period CAP3 EU | D56: T3PA | E56: successful | F56: 66.17 | G56: 64.94 | H56: 72 | I56: 66.24 | J56: 65.98 | K56: 2510500 | L56: 3528500 | M56: 73 | N56: 27 | O56: 4.06 | P56: 48336 | Q56: 196028 | R56: 286908 | S56: 167367 | T56: 266264 | U56: 1.41 | V56: 18 | W56: 15 | X56: 166119785 | Y56: EU | Z56: 2448290 | AA56: 4201795 | AB56: 6749340 | AC56: 628615 | AD56: 4466475 | AF56: 2282865 | AG56: 2084355 | AH56: 8271250 | AI56: 20049510 | AJ56: 3242330 | AK56: 11712090 | AL56: 893295 | AM56: 3804775 | AN56: 0 | AO56: 19453980 | AP56: 0 | AQ56: 20181850 | AR56: 0 | AS56: 661700 | AT56: 0 | AU56: 496275 | AV56: 33250425 | AW56: 231595 | AX56: 7179445 | AY56: 1389570 | BA56: 4168710 | BB56: 3275415 | BC56: 1753505 | BD56: 1058720 | BE56: 2183610
A57: 44837 | B57: 44837.459 | C57: Auction 4. Period CAP3 EU | D57: T3PA | E57: successful | F57: 64.45 | G57: 45 | H57: 67.19 | I57: 64.21 | J57: 64.63 | K57: 2510500 | L57: 4440500 | M57: 71 | N57: 42 | O57: 4.44 | P57: 62542 | Q57: 277531 | R57: 305481 | S57: 179321 | T57: 246335 | U57: 1.77 | V57: 16 | W57: 14 | X57: 161801725 | Y57: EU | Z57: 2384650 | AA57: 4092575 | AB57: 6573900 | AC57: 612275 | AD57: 4350375 | AF57: 2223525 | AG57: 2030175 | AH57: 8056250 | AI57: 19528350 | AJ57: 3158050 | AK57: 11407650 | AL57: 870075 | AM57: 3705875 | AN57: 0 | AO57: 18948300 | AP57: 0 | AQ57: 19657250 | AR57: 0 | AS57: 644500 | AT57: 0 | AU57: 483375 | AV57: 32386125 | AW57: 225575 | AX57: 6992825 | AY57: 1353450 | BA57: 4060350 | BB57: 3190275 | BC57: 1707925 | BD57: 1031200 | BE57: 2126850
A58: 44834 | B58: 44834.459 | C58: Auction 4. Period DE | D58: T3PA | E58: successful | F58: 66.87 | G58: 45 | H58: 70.12 | I58: 66.75 | J58: 67.25 | K58: 1861500 | L58: 3037500 | M58: 60 | N58: 37 | O58: 4.29 | P58: 50625 | Q58: 216964 | R58: 290482 | S58: 206833 | T58: 231478 | U58: 1.63 | V58: 14 | W58: 9 | X58: 124478505 | Y58: DE | AE58: 124478505
A59: 44833 | B59: 44833.459 | C59: Auction 4. Period CAP3 EU | D59: T3PA | E59: successful | F59: 64.7 | G59: 45 | H59: 75 | I59: 64.18 | J59: 64.28 | K59: 2510500 | L59: 4296000 | M59: 69 | N59: 25 | O59: 4.31 | P59: 62261 | Q59: 268500 | R59: 336423 | S59: 251050 | T59: 271479 | U59: 1.71 | V59: 16 | W59: 10 | X59: 162429350 | Y59: EU | Z59: 2393900 | AA59: 4108450 | AB59: 6599400 | AC59: 614650 | AD59: 4367250 | AF59: 2232150 | AG59: 2038050 | AH59: 8087500 | AI59: 19604100 | AJ59: 3170300 | AK59: 11451900 | AL59: 873450 | AM59: 3720250 | AN59: 0 | AO59: 19021800 | AP59: 0 | AQ59: 19733500 | AR59: 0 | AS59: 647000 | AT59: 0 | AU59: 485250 | AV59: 32511750 | AW59: 226450 | AX59: 7019950 | AY59: 1358700 | BA59: 4076100 | BB59: 3202650 | BC59: 1714550 | BD59: 1035200 | BE59: 2135100
A60: 44832 | B60: 44832.459 | C60: Auction 4. Period CAP3 PL | D60: T3PA | E60: successful | F60: 64.71 | G60: 45 | H60: 75 | I60: 64.82 | J60: 64.83 | K60: 3101500 | L60: 4663000 | M60: 76 | N60: 44 | O60: 4.47 | P60: 61355 | Q60: 274294 | R60: 304113 | S60: 221536 | T60: 256101 | U60: 1.5 | V60: 17 | W60: 14 | X60: 200698065 | Y60: PL | AZ60: 200698065
A61: 44831 | B61: 44831.459 | C61: Auction 4. Period CAP3 EU | D61: T3PA | E61: successful | F61: 67.7 | G61: 45 | H61: 80 | I61: 67.43 | J61: 67.57 | K61: 2510500 | L61: 4831500 | M61: 81 | N61: 36 | O61: 4.05 | P61: 59648 | Q61: 241575 | R61: 274427 | S61: 156906 | T61: 193158 | U61: 1.92 | V61: 20 | W61: 16 | X61: 169960850 | Y61: EU | Z61: 2504900 | AA61: 4298950 | AB61: 6905400 | AC61: 643150 | AD61: 4569750 | AF61: 2335650 | AG61: 2132550 | AH61: 8462500 | AI61: 20513100 | AJ61: 3317300 | AK61: 11982900 | AL61: 913950 | AM61: 3892750 | AN61: 0 | AO61: 19903800 | AP61: 0 | AQ61: 20648500 | AR61: 0 | AS61: 677000 | AT61: 0 | AU61: 507750 | AV61: 34019250 | AW61: 236950 | AX61: 7345450 | AY61: 1421700 | BA61: 4265100 | BB61: 3351150 | BC61: 1794050 | BD61: 1083200 | BE61: 2234100
A62: 44830 | B62: 44830.459 | C62: Auction 4. Period CAP3 EU | D62: T3PA | E62: successful | F62: 66.02 | G62: 58.98 | H62: 75 | I62: 65.55 | J62: 65.45 | K62: 2510500 | L62: 4546500 | M62: 67 | N62: 13 | O62: 4.19 | P62: 67858 | Q62: 284156 | R62: 438621 | S62: 278944 | T62: 457267 | U62: 1.81 | V62: 16 | W62: 9 | X62: 165743210 | Y62: EU | Z62: 2442740 | AA62: 4192270 | AB62: 6734040 | AC62: 627190 | AD62: 4456350 | AF62: 2277690 | AG62: 2079630 | AH62: 8252500 | AI62: 20004060 | AJ62: 3234980 | AK62: 11685540 | AL62: 891270 | AM62: 3796150 | AN62: 0 | AO62: 19409880 | AP62: 0 | AQ62: 20136100 | AR62: 0 | AS62: 660200 | AT62: 0 | AU62: 495150 | AV62: 33175050 | AW62: 231070 | AX62: 7163170 | AY62: 1386420 | BA62: 4159260 | BB62: 3267990 | BC62: 1749530 | BD62: 1056320 | BE62: 2178660
A63: 44827 | B63: 44827.459 | C63: Auction 4. Period DE | D63: T3PA | E63: successful | F63: 67.56 | G63: 45 | H63: 75 | I63: 67.69 | J63: 68.01 | K63: 1861500 | L63: 2958000 | M63: 53 | N63: 39 | O63: 3.79 | P63: 55811 | Q63: 211286 | R63: 291236 | S63: 143192 | T63: 220868 | U63: 1.59 | V63: 14 | W63: 13 | X63: 125762940 | Y63: DE | AE63: 125762940
A64: 44826 | B64: 44826.459 | C64: Auction 4. Period CAP3 EU | D64: T3PA | E64: successful | F64: 69.88 | G64: 45 | H64: 76 | I64: 69.52 | J64: 69.71 | K64: 2511500 | L64: 4229000 | M64: 73 | N64: 28 | O64: 3.65 | P64: 57932 | Q64: 211450 | R64: 314356 | S64: 167433 | T64: 256313 | U64: 1.68 | V64: 20 | W64: 15 | X64: 175503620 | Y64: EU | Z64: 2585560 | AA64: 4437380 | AB64: 7127760 | AC64: 663860 | AD64: 4716900 | AF64: 2410860 | AG64: 2201220 | AH64: 8735000 | AI64: 21173640 | AJ64: 3424120 | AK64: 12368760 | AL64: 943380 | AM64: 4018100 | AN64: 0 | AO64: 20544720 | AP64: 0 | AQ64: 21313400 | AR64: 69880 | AS64: 698800 | AT64: 0 | AU64: 524100 | AV64: 35114700 | AW64: 244580 | AX64: 7581980 | AY64: 1467480 | BA64: 4402440 | BB64: 3459060 | BC64: 1851820 | BD64: 1118080 | BE64: 2306040
A65: 44825 | B65: 44825.459 | C65: Auction 4. Period CAP3 NIR | D65: T3PA | E65: successful | F65: 70.39 | G65: 45 | H65: 80 | I65: 69.38 | J65: 69.91 | K65: 929000 | L65: 2724000 | M65: 66 | N65: 18 | O65: 3.88 | P65: 41273 | Q65: 160235 | R65: 238017 | S65: 116125 | T65: 130967 | U65: 2.93 | V65: 17 | W65: 8 | X65: 65392310 | Y65: XI | BF65: 65392310
A66: 44824 | B66: 44824.459 | C66: Auction 4. Period CAP3 EU | D66: T3PA | E66: successful | F66: 70.38 | G66: 45 | H66: 80 | I66: 69.82 | J66: 69.98 | K66: 2510500 | L66: 5304500 | M66: 81 | N66: 22 | O66: 3.86 | P66: 65488 | Q66: 252595 | R66: 439275 | S66: 193115 | T66: 275286 | U66: 2.11 | V66: 21 | W66: 13 | X66: 176688990 | Y66: EU | Z66: 2604060 | AA66: 4469130 | AB66: 7178760 | AC66: 668610 | AD66: 4750650 | AF66: 2428110 | AG66: 2216970 | AH66: 8797500 | AI66: 21325140 | AJ66: 3448620 | AK66: 12457260 | AL66: 950130 | AM66: 4046850 | AN66: 0 | AO66: 20691720 | AP66: 0 | AQ66: 21465900 | AR66: 0 | AS66: 703800 | AT66: 0 | AU66: 527850 | AV66: 35365950 | AW66: 246330 | AX66: 7636230 | AY66: 1477980 | BA66: 4433940 | BB66: 3483810 | BC66: 1865070 | BD66: 1126080 | BE66: 2322540
A67: 44823 | B67: 44823.459 | C67: Auction 4. Period CAP3 EU | D67: T3PA | E67: successful | F67: 71.11 | G67: 45 | H67: 80 | I67: 70.71 | J67: 70.88 | K67: 2510500 | L67: 6251000 | M67: 90 | N67: 35 | O67: 5.29 | P67: 69456 | Q67: 367706 | R67: 661058 | S67: 209208 | T67: 351974 | U67: 2.49 | V67: 17 | W67: 12 | X67: 178521655 | Y67: EU | Z67: 2631070 | AA67: 4515485 | AB67: 7253220 | AC67: 675545 | AD67: 4799925 | AF67: 2453295 | AG67: 2239965 | AH67: 8888750 | AI67: 21546330 | AJ67: 3484390 | AK67: 12586470 | AL67: 959985 | AM67: 4088825 | AN67: 0 | AO67: 20906340 | AP67: 0 | AQ67: 21688550 | AR67: 0 | AS67: 711100 | AT67: 0 | AU67: 533325 | AV67: 35732775 | AW67: 248885 | AX67: 7715435 | AY67: 1493310 | BA67: 4479930 | BB67: 3519945 | BC67: 1884415 | BD67: 1137760 | BE67: 2346630
A68: 44820 | B68: 44820.459 | C68: Auction 4. Period DE | D68: T3PA | E68: successful | F68: 71 | G68: 45 | H68: 75 | I68: 70.27 | J68: 70.78 | K68: 1861500 | L68: 3102500 | M68: 75 | N68: 32 | O68: 4.41 | P68: 41367 | Q68: 182500 | R68: 190978 | S68: 132964 | T68: 178637 | U68: 1.67 | V68: 17 | W68: 14 | X68: 132166500 | Y68: DE | AE68: 132166500
A69: 44819 | B69: 44819.459 | C69: Auction 4. Period CAP3 EU | D69: T3PA | E69: successful | F69: 70.84 | G69: 45 | H69: 80 | I69: 70.34 | J69: 70.58 | K69: 2510500 | L69: 3550500 | M69: 84 | N69: 36 | O69: 4.67 | P69: 42268 | Q69: 197250 | R69: 240667 | S69: 209208 | T69: 261319 | U69: 1.41 | V69: 18 | W69: 12 | X69: 177843820 | Y69: EU | Z69: 2621080 | AA69: 4498340 | AB69: 7225680 | AC69: 672980 | AD69: 4781700 | AF69: 2443980 | AG69: 2231460 | AH69: 8855000 | AI69: 21464520 | AJ69: 3471160 | AK69: 12538680 | AL69: 956340 | AM69: 4073300 | AN69: 0 | AO69: 20826960 | AP69: 0 | AQ69: 21606200 | AR69: 0 | AS69: 708400 | AT69: 0 | AU69: 531300 | AV69: 35597100 | AW69: 247940 | AX69: 7686140 | AY69: 1487640 | BA69: 4462920 | BB69: 3506580 | BC69: 1877260 | BD69: 1133440 | BE69: 2337720
A70: 44818 | B70: 44818.459 | C70: Auction 4. Period CAP3 PL | D70: T3PA | E70: successful | F70: 68.29 | G70: 45 | H70: 75 | I70: 68.24 | J70: 68.22 | K70: 3101500 | L70: 5838500 | M70: 83 | N70: 39 | O70: 4.15 | P70: 70343 | Q70: 291925 | R70: 419520 | S70: 182441 | T70: 246809 | U70: 1.88 | V70: 20 | W70: 17 | X70: 211801435 | Y70: PL | AZ70: 211801435
A71: 44817 | B71: 44817.459 | C71: Auction 4. Period CAP3 EU | D71: T3PA | E71: successful | F71: 70.48 | G71: 45 | H71: 100 | I71: 70.45 | J71: 70.61 | K71: 2510500 | L71: 4820000 | M71: 87 | N71: 49 | O71: 4.14 | P71: 55402 | Q71: 229524 | R71: 395025 | S71: 139472 | T71: 173860 | U71: 1.92 | V71: 21 | W71: 18 | X71: 176940040 | Y71: EU | Z71: 2607760 | AA71: 4475480 | AB71: 7188960 | AC71: 669560 | AD71: 4757400 | AF71: 2431560 | AG71: 2220120 | AH71: 8810000 | AI71: 21355440 | AJ71: 3453520 | AK71: 12474960 | AL71: 951480 | AM71: 4052600 | AN71: 0 | AO71: 20721120 | AP71: 0 | AQ71: 21496400 | AR71: 0 | AS71: 704800 | AT71: 0 | AU71: 528600 | AV71: 35416200 | AW71: 246680 | AX71: 7647080 | AY71: 1480080 | BA71: 4440240 | BB71: 3488760 | BC71: 1867720 | BD71: 1127680 | BE71: 2325840
A72: 44816 | B72: 44816.459 | C72: Auction 4. Period CAP3 EU | D72: T3PA | E72: successful | F72: 65.96 | G72: 45 | H72: 77.5 | I72: 65.83 | J72: 65.55 | K72: 2510500 | L72: 5241500 | M72: 78 | N72: 23 | O72: 4.11 | P72: 67199 | Q72: 275868 | R72: 446277 | S72: 278944 | T72: 263028 | U72: 2.09 | V72: 19 | W72: 9 | X72: 165592580 | Y72: EU | Z72: 2440520 | AA72: 4188460 | AB72: 6727920 | AC72: 626620 | AD72: 4452300 | AF72: 2275620 | AG72: 2077740 | AH72: 8245000 | AI72: 19985880 | AJ72: 3232040 | AK72: 11674920 | AL72: 890460 | AM72: 3792700 | AN72: 0 | AO72: 19392240 | AP72: 0 | AQ72: 20117800 | AR72: 0 | AS72: 659600 | AT72: 0 | AU72: 494700 | AV72: 33144900 | AW72: 230860 | AX72: 7156660 | AY72: 1385160 | BA72: 4155480 | BB72: 3265020 | BC72: 1747940 | BD72: 1055360 | BE72: 2176680
A73: 44813 | B73: 44813.459 | C73: Auction 4. Period DE | D73: T3PA | E73: successful | F73: 65.21 | G73: 45 | H73: 74.8 | I73: 65.83 | J73: 65.47 | K73: 1861500 | L73: 4143000 | M73: 69 | N73: 48 | O73: 4.06 | P73: 60043 | Q73: 243706 | R73: 417777 | S73: 124100 | T73: 153723 | U73: 2.23 | V73: 17 | W73: 15 | X73: 121388415 | Y73: DE | AE73: 121388415
A74: 44811 | B74: 44811.459 | C74: EUAA Auction CAP3 EU | D74: EAA3 | E74: successful | F74: 69.06 | G74: 45 | H74: 72 | I74: 68.84 | J74: 69.76 | K74: 600000 | L74: 634000 | M74: 23 | N74: 22 | O74: 3.83 | P74: 27565 | Q74: 105667 | R74: 96965 | S74: 100000 | T74: 96334 | U74: 1.06 | V74: 6 | W74: 6 | X74: 41436000 | Y74: EU | Z74: 1070430 | AA74: 1484790 | AB74: 483420 | AC74: 345300 | AD74: 517950 | AF74: 1312140 | AG74: 138120 | AH74: 2658810 | AI74: 7596600 | AJ74: 1104960 | AK74: 5766510 | AL74: 379830 | AM74: 483420 | AN74: 1001370 | AP74: 483420 | AQ74: 6284460 | AR74: 0 | AS74: 241710 | AT74: 172650 | AU74: 276240 | AW74: 310770 | AX74: 2175390 | AY74: 2140860 | BA74: 2002740 | BB74: 966840 | BC74: 1899150 | BD74: 69060 | BE74: 69060
A75: 44810 | B75: 44810.459 | C75: Auction 4. Period CAP3 EU | D75: T3PA | E75: successful | F75: 71.05 | G75: 45 | H75: 100 | I75: 70.95 | J75: 70.98 | K75: 2510500 | L75: 5663000 | M75: 74 | N75: 34 | O75: 3.7 | P75: 76527 | Q75: 283150 | R75: 425804 | S75: 167367 | T75: 240113 | U75: 2.26 | V75: 20 | W75: 15 | X75: 178371025 | Y75: EU | Z75: 2628850 | AA75: 4511675 | AB75: 7247100 | AC75: 674975 | AD75: 4795875 | AF75: 2451225 | AG75: 2238075 | AH75: 8881250 | AI75: 21528150 | AJ75: 3481450 | AK75: 12575850 | AL75: 959175 | AM75: 4085375 | AN75: 0 | AO75: 20888700 | AP75: 0 | AQ75: 21670250 | AR75: 0 | AS75: 710500 | AT75: 0 | AU75: 532875 | AV75: 35702625 | AW75: 248675 | AX75: 7708925 | AY75: 1492050 | BA75: 4476150 | BB75: 3516975 | BC75: 1882825 | BD75: 1136800 | BE75: 2344650
A76: 44809 | B76: 44809.459 | C76: Auction 4. Period CAP3 EU | D76: T3PA | E76: successful | F76: 73.75 | G76: 45 | H76: 77 | I76: 73.16 | J76: 73.81 | K76: 2510500 | L76: 5335000 | M76: 72 | N76: 40 | O76: 3.6 | P76: 74097 | Q76: 266750 | R76: 430312 | S76: 139472 | T76: 221500 | U76: 2.13 | V76: 20 | W76: 18 | X76: 185149375 | Y76: EU | Z76: 2728750 | AA76: 4683125 | AB76: 7522500 | AC76: 700625 | AD76: 4978125 | AF76: 2544375 | AG76: 2323125 | AH76: 9218750 | AI76: 22346250 | AJ76: 3613750 | AK76: 13053750 | AL76: 995625 | AM76: 4240625 | AN76: 0 | AO76: 21682500 | AP76: 0 | AQ76: 22493750 | AR76: 0 | AS76: 737500 | AT76: 0 | AU76: 553125 | AV76: 37059375 | AW76: 258125 | AX76: 8001875 | AY76: 1548750 | BA76: 4646250 | BB76: 3650625 | BC76: 1954375 | BD76: 1180000 | BE76: 2433750
A77: 44806 | B77: 44806.459 | C77: Auction 4. Period DE | D77: T3PA | E77: successful | F77: 78.41 | G77: 45 | H77: 84 | I77: 78.15 | J77: 78.67 | K77: 1861500 | L77: 2933500 | M77: 72 | N77: 47 | O77: 4.24 | P77: 40743 | Q77: 172559 | R77: 238153 | S77: 116344 | T77: 219920 | U77: 1.58 | V77: 17 | W77: 16 | X77: 145960215 | Y77: DE | AE77: 145960215
A78: 44805 | B78: 44805.459 | C78: Auction 4. Period CAP3 EU | D78: T3PA | E78: successful | F78: 77.01 | G78: 63.41 | H78: 80 | I78: 77.1 | J78: 77.05 | K78: 2510500 | L78: 4576500 | M78: 69 | N78: 43 | O78: 4.31 | P78: 66326 | Q78: 286031 | R78: 463455 | S78: 156906 | T78: 240601 | U78: 1.82 | V78: 16 | W78: 16 | X78: 193333605 | Y78: EU | Z78: 2849370 | AA78: 4890135 | AB78: 7855020 | AC78: 731595 | AD78: 5198175 | AF78: 2656845 | AG78: 2425815 | AH78: 9626250 | AI78: 23334030 | AJ78: 3773490 | AK78: 13630770 | AL78: 1039635 | AM78: 4428075 | AN78: 0 | AO78: 22640940 | AP78: 0 | AQ78: 23488050 | AR78: 0 | AS78: 770100 | AT78: 0 | AU78: 577575 | AV78: 38697525 | AW78: 269535 | AX78: 8355585 | AY78: 1617210 | BA78: 4851630 | BB78: 3811995 | BC78: 2040765 | BD78: 1232160 | BE78: 2541330
A79: 44804 | B79: 44804.459 | C79: Auction 4. Period CAP3 PL | D79: T3PA | E79: successful | F79: 78.96 | G79: 45 | H79: 84 | I79: 78.43 | J79: 79.02 | K79: 1334500 | L79: 3447000 | M79: 59 | N79: 33 | O79: 3.47 | P79: 58424 | Q79: 202765 | R79: 413321 | S79: 83406 | T79: 107636 | U79: 2.58 | V79: 17 | W79: 16 | X79: 105372120 | Y79: PL | AZ79: 105372120
A80: 44803 | B80: 44803.459 | C80: Auction 4. Period CAP3 EU | D80: T3PA | E80: successful | F80: 85.13 | G80: 70 | H80: 90 | I80: 85 | J80: 85.42 | K80: 1295500 | L80: 3140000 | M80: 47 | N80: 34 | O80: 3.92 | P80: 66809 | Q80: 261667 | R80: 480175 | S80: 117773 | T80: 145091 | U80: 2.42 | V80: 12 | W80: 11 | X80: 110285915 | Y80: EU | Z80: 2511335 | AA80: 553345 | AB80: 4682150 | AC80: 978995 | AD80: 3234940 | AF80: 723605 | AG80: 1660035 | AH80: 4299065 | AI80: 11790505 | AJ80: 1617470 | AK80: 7023225 | AL80: 1021560 | AM80: 2596465 | AN80: 0 | AO80: 12514110 | AP80: 0 | AQ80: 13195150 | AR80: 0 | AS80: 1191820 | AT80: 0 | AU80: 425650 | AV80: 21325065 | AW80: 681040 | AX80: 6129360 | AY80: 42565 | BA80: 2894420 | BB80: 3277505 | BC80: 1574905 | BD80: 808735 | BE80: 3532895
A81: 44802 | B81: 44802.459 | C81: Auction 4. Period CAP3 EU | D81: T3PA | E81: successful | F81: 88.81 | G81: 45 | H81: 91 | I81: 87.63 | J81: 88.79 | K81: 1146500 | L81: 3253000 | M81: 56 | N81: 28 | O81: 4.31 | P81: 58089 | Q81: 250231 | R81: 477082 | S81: 114650 | T81: 183911 | U81: 2.84 | V81: 13 | W81: 10 | X81: 101820665 | Y81: EU | Z81: 1465365 | AA81: 577265 | AB81: 5284195 | AC81: 444050 | AD81: 2619895 | AF81: 310835 | AG81: 1287745 | AH81: 5239790 | AI81: 12788640 | AJ81: 1110125 | AK81: 7282420 | AL81: 666075 | AM81: 1554175 | AN81: 0 | AO81: 13055070 | AP81: 0 | AQ81: 12611020 | AR81: 0 | AS81: 488455 | AT81: 0 | AU81: 355240 | AV81: 22246905 | AW81: 177620 | AX81: 4484905 | AY81: 133215 | BA81: 2664300 | BB81: 1865010 | BC81: 1065720 | BD81: 666075 | BE81: 1376555
A82: 44799 | B82: 44799.459 | C82: Auction 4. Period DE | D82: T3PA | E82: successful | F82: 89.56 | G82: 45 | H82: 91 | I82: 88.2 | J82: 88.86 | K82: 982000 | L82: 1940000 | M82: 60 | N82: 12 | O82: 4 | P82: 32333 | Q82: 129333 | R82: 132663 | S82: 109111 | T82: 144310 | U82: 1.98 | V82: 15 | W82: 9 | X82: 87947920 | Y82: DE | AE82: 87947920
A83: 44798 | B83: 44798.459 | C83: Auction 4. Period CAP3 EU | D83: T3PA | E83: successful | F83: 89.3 | G83: 45 | H83: 99 | I83: 86.68 | J83: 88.11 | K83: 1146500 | L83: 3756000 | M83: 61 | N83: 9 | O83: 3.59 | P83: 61574 | Q83: 220941 | R83: 422349 | S83: 191083 | T83: 171830 | U83: 3.28 | V83: 17 | W83: 6 | X83: 102382450 | Y83: EU | Z83: 1473450 | AA83: 580450 | AB83: 5313350 | AC83: 446500 | AD83: 2634350 | AF83: 312550 | AG83: 1294850 | AH83: 5268700 | AI83: 12859200 | AJ83: 1116250 | AK83: 7322600 | AL83: 669750 | AM83: 1562750 | AN83: 0 | AO83: 13127100 | AP83: 0 | AQ83: 12680600 | AR83: 0 | AS83: 491150 | AT83: 0 | AU83: 357200 | AV83: 22369650 | AW83: 178600 | AX83: 4509650 | AY83: 133950 | BA83: 2679000 | BB83: 1875300 | BC83: 1071600 | BD83: 669750 | BE83: 1384150
A84: 44796 | B84: 44796.46 | C84: Auction 4. Period CAP3 EU | D84: T3PA | E84: successful | F84: 92.52 | G84: 45 | H84: 95.5 | I84: 91.28 | J84: 92.69 | K84: 1146500 | L84: 3161500 | M84: 50 | N84: 30 | O84: 3.57 | P84: 63230 | Q84: 225821 | R84: 453708 | S84: 114650 | T84: 136214 | U84: 2.76 | V84: 14 | W84: 10 | X84: 106074180 | Y84: EU | Z84: 1526580 | AA84: 601380 | AB84: 5504940 | AC84: 462600 | AD84: 2729340 | AF84: 323820 | AG84: 1341540 | AH84: 5458680 | AI84: 13322880 | AJ84: 1156500 | AK84: 7586640 | AL84: 693900 | AM84: 1619100 | AN84: 0 | AO84: 13600440 | AP84: 0 | AQ84: 13137840 | AR84: 0 | AS84: 508860 | AT84: 0 | AU84: 370080 | AV84: 23176260 | AW84: 185040 | AX84: 4672260 | AY84: 138780 | BA84: 2775600 | BB84: 1942920 | BC84: 1110240 | BD84: 693900 | BE84: 1434060
A85: 44795 | B85: 44795.459 | C85: Auction 4. Period CAP3 EU | D85: T3PA | E85: successful | F85: 97.5 | G85: 79.93 | H85: 104 | I85: 97.42 | J85: 97.07 | K85: 1146500 | L85: 3565500 | M85: 67 | N85: 21 | O85: 4.19 | P85: 53216 | Q85: 222844 | R85: 421774 | S85: 163786 | T85: 140406 | U85: 3.11 | V85: 16 | W85: 7 | X85: 111783750 | Y85: EU | Z85: 1608750 | AA85: 633750 | AB85: 5801250 | AC85: 487500 | AD85: 2876250 | AF85: 341250 | AG85: 1413750 | AH85: 5752500 | AI85: 14040000 | AJ85: 1218750 | AK85: 7995000 | AL85: 731250 | AM85: 1706250 | AN85: 0 | AO85: 14332500 | AP85: 0 | AQ85: 13845000 | AR85: 0 | AS85: 536250 | AT85: 0 | AU85: 390000 | AV85: 24423750 | AW85: 195000 | AX85: 4923750 | AY85: 146250 | BA85: 2925000 | BB85: 2047500 | BC85: 1170000 | BD85: 731250 | BE85: 1511250
A86: 44792 | B86: 44792.459 | C86: Auction 4. Period DE | D86: T3PA | E86: successful | F86: 96.87 | G86: 45 | H86: 99 | I86: 94.69 | J86: 95.65 | K86: 972000 | L86: 2810000 | M86: 53 | N86: 5 | O86: 3.12 | P86: 53019 | Q86: 165294 | R86: 228470 | S86: 324000 | T86: 301957 | U86: 2.89 | V86: 17 | W86: 3 | X86: 94157640 | Y86: DE | AE86: 94157640
A87: 44791 | B87: 44791.459 | C87: Auction 4. Period CAP3 EU | D87: T3PA | E87: successful | F87: 94 | G87: 45 | H87: 97 | I87: 91.93 | J87: 93.4 | K87: 1146500 | L87: 4051500 | M87: 75 | N87: 15 | O87: 4.17 | P87: 54020 | Q87: 225083 | R87: 400757 | S87: 114650 | T87: 139254 | U87: 3.53 | V87: 18 | W87: 10 | X87: 107771000 | Y87: EU | Z87: 1551000 | AA87: 611000 | AB87: 5593000 | AC87: 470000 | AD87: 2773000 | AF87: 329000 | AG87: 1363000 | AH87: 5546000 | AI87: 13536000 | AJ87: 1175000 | AK87: 7708000 | AL87: 705000 | AM87: 1645000 | AN87: 0 | AO87: 13818000 | AP87: 0 | AQ87: 13348000 | AR87: 0 | AS87: 517000 | AT87: 0 | AU87: 376000 | AV87: 23547000 | AW87: 188000 | AX87: 4747000 | AY87: 141000 | BA87: 2820000 | BB87: 1974000 | BC87: 1128000 | BD87: 705000 | BE87: 1457000
A88: 44790 | B88: 44790.459 | C88: Auction 4. Period CAP3 PL | D88: T3PA | E88: successful | F88: 94.07 | G88: 45 | H88: 97 | I88: 92.2 | J88: 94.04 | K88: 1329000 | L88: 3595500 | M88: 53 | N88: 26 | O88: 3.12 | P88: 67840 | Q88: 211500 | R88: 417103 | S88: 120818 | T88: 146852 | U88: 2.71 | V88: 17 | W88: 11 | X88: 125019030 | Y88: PL | AZ88: 125019030
A89: 44789 | B89: 44789.459 | C89: Auction 4. Period CAP3 EU | D89: T3PA | E89: successful | F89: 90.64 | G89: 45 | H89: 94 | I89: 88.96 | J89: 90.16 | K89: 1146500 | L89: 3591500 | M89: 52 | N89: 12 | O89: 3.47 | P89: 69067 | Q89: 239433 | R89: 436141 | S89: 143313 | T89: 151627 | U89: 3.13 | V89: 15 | W89: 8 | X89: 103918760 | Y89: EU | Z89: 1495560 | AA89: 589160 | AB89: 5393080 | AC89: 453200 | AD89: 2673880 | AF89: 317240 | AG89: 1314280 | AH89: 5347760 | AI89: 13052160 | AJ89: 1133000 | AK89: 7432480 | AL89: 679800 | AM89: 1586200 | AN89: 0 | AO89: 13324080 | AP89: 0 | AQ89: 12870880 | AR89: 0 | AS89: 498520 | AT89: 0 | AU89: 362560 | AV89: 22705320 | AW89: 181280 | AX89: 4577320 | AY89: 135960 | BA89: 2719200 | BB89: 1903440 | BC89: 1087680 | BD89: 679800 | BE89: 1404920
A90: 44788 | B90: 44788.459 | C90: Auction 4. Period CAP3 EU | D90: T3PA | E90: successful | F90: 89.5 | G90: 45 | H90: 92.3 | I90: 88.08 | J90: 89.01 | K90: 1146500 | L90: 3180000 | M90: 60 | N90: 12 | O90: 3.53 | P90: 53000 | Q90: 187059 | R90: 255535 | S90: 163786 | T90: 87284 | U90: 2.77 | V90: 17 | W90: 7 | X90: 102611750 | Y90: EU | Z90: 1476750 | AA90: 581750 | AB90: 5325250 | AC90: 447500 | AD90: 2640250 | AF90: 313250 | AG90: 1297750 | AH90: 5280500 | AI90: 12888000 | AJ90: 1118750 | AK90: 7339000 | AL90: 671250 | AM90: 1566250 | AN90: 0 | AO90: 13156500 | AP90: 0 | AQ90: 12709000 | AR90: 0 | AS90: 492250 | AT90: 0 | AU90: 358000 | AV90: 22419750 | AW90: 179000 | AX90: 4519750 | AY90: 134250 | BA90: 2685000 | BB90: 1879500 | BC90: 1074000 | BD90: 671250 | BE90: 1387250
A91: 44785 | B91: 44785.459 | C91: Auction 4. Period DE | D91: T3PA | E91: successful | F91: 87.3 | G91: 45 | H91: 90 | I91: 85.79 | J91: 86.84 | K91: 972000 | L91: 3204000 | M91: 70 | N91: 18 | O91: 3.89 | P91: 45771 | Q91: 178000 | R91: 195315 | S91: 121500 | T91: 79289 | U91: 3.3 | V91: 18 | W91: 8 | X91: 84855600 | Y91: DE | AE91: 84855600
A92: 44784 | B92: 44784.459 | C92: Auction 4. Period CAP3 EU | D92: T3PA | E92: successful | F92: 86.35 | G92: 45 | H92: 89.75 | I92: 84.6 | J92: 86.05 | K92: 1146500 | L92: 3863000 | M92: 65 | N92: 18 | O92: 2.95 | P92: 59431 | Q92: 175591 | R92: 370905 | S92: 95542 | T92: 148307 | U92: 3.37 | V92: 22 | W92: 12 | X92: 99000275 | Y92: EU | Z92: 1424775 | AA92: 561275 | AB92: 5137825 | AC92: 431750 | AD92: 2547325 | AF92: 302225 | AG92: 1252075 | AH92: 5094650 | AI92: 12434400 | AJ92: 1079375 | AK92: 7080700 | AL92: 647625 | AM92: 1511125 | AN92: 0 | AO92: 12693450 | AP92: 0 | AQ92: 12261700 | AR92: 0 | AS92: 474925 | AT92: 0 | AU92: 345400 | AV92: 21630675 | AW92: 172700 | AX92: 4360675 | AY92: 129525 | BA92: 2590500 | BB92: 1813350 | BC92: 1036200 | BD92: 647625 | BE92: 1338425
A93: 44782 | B93: 44782.459 | C93: Auction 4. Period CAP3 EU | D93: T3PA | E93: successful | F93: 84.06 | G93: 68.57 | H93: 88 | I93: 83.52 | J93: 83.38 | K93: 1146500 | L93: 4066000 | M93: 70 | N93: 15 | O93: 3.89 | P93: 58086 | Q93: 225889 | R93: 465483 | S93: 229300 | T93: 101667 | U93: 3.55 | V93: 18 | W93: 5 | X93: 96374790 | Y93: EU | Z93: 1386990 | AA93: 546390 | AB93: 5001570 | AC93: 420300 | AD93: 2479770 | AF93: 294210 | AG93: 1218870 | AH93: 4959540 | AI93: 12104640 | AJ93: 1050750 | AK93: 6892920 | AL93: 630450 | AM93: 1471050 | AN93: 0 | AO93: 12356820 | AP93: 0 | AQ93: 11936520 | AR93: 0 | AS93: 462330 | AT93: 0 | AU93: 336240 | AV93: 21057030 | AW93: 168120 | AX93: 4245030 | AY93: 126090 | BA93: 2521800 | BB93: 1765260 | BC93: 1008720 | BD93: 630450 | BE93: 1302930
A94: 44781 | B94: 44781.459 | C94: Auction 4. Period CAP3 EU | D94: T3PA | E94: successful | F94: 84.6 | G94: 45 | H94: 88.6 | I94: 83.7 | J94: 84.4 | K94: 1146500 | L94: 4141000 | M94: 72 | N94: 25 | O94: 4 | P94: 57514 | Q94: 230056 | R94: 468257 | S94: 114650 | T94: 149911 | U94: 3.61 | V94: 18 | W94: 10 | X94: 96993900 | Y94: EU | Z94: 1395900 | AA94: 549900 | AB94: 5033700 | AC94: 423000 | AD94: 2495700 | AF94: 296100 | AG94: 1226700 | AH94: 4991400 | AI94: 12182400 | AJ94: 1057500 | AK94: 6937200 | AL94: 634500 | AM94: 1480500 | AN94: 0 | AO94: 12436200 | AP94: 0 | AQ94: 12013200 | AR94: 0 | AS94: 465300 | AT94: 0 | AU94: 338400 | AV94: 21192300 | AW94: 169200 | AX94: 4272300 | AY94: 126900 | BA94: 2538000 | BB94: 1776600 | BC94: 1015200 | BD94: 634500 | BE94: 1311300
A95: 44778 | B95: 44778.459 | C95: Auction 4. Period DE | D95: T3PA | E95: successful | F95: 84.5 | G95: 45 | H95: 86.82 | I95: 83.03 | J95: 84.28 | K95: 972000 | L95: 2383000 | M95: 40 | N95: 16 | O95: 3.08 | P95: 59575 | Q95: 183308 | R95: 300017 | S95: 97200 | T95: 175069 | U95: 2.45 | V95: 13 | W95: 10 | X95: 82134000 | Y95: DE | AE95: 82134000
A96: 44777 | B96: 44777.459 | C96: Auction 4. Period CAP3 EU | D96: T3PA | E96: successful | F96: 83.81 | G96: 45 | H96: 90 | I96: 82.71 | J96: 83.84 | K96: 1146500 | L96: 3642000 | M96: 47 | N96: 25 | O96: 3.36 | P96: 77489 | Q96: 260143 | R96: 517300 | S96: 104227 | T96: 128630 | U96: 3.18 | V96: 14 | W96: 11 | X96: 96088165 | Y96: EU | Z96: 1382865 | AA96: 544765 | AB96: 4986695 | AC96: 419050 | AD96: 2472395 | AF96: 293335 | AG96: 1215245 | AH96: 4944790 | AI96: 12068640 | AJ96: 1047625 | AK96: 6872420 | AL96: 628575 | AM96: 1466675 | AN96: 0 | AO96: 12320070 | AP96: 0 | AQ96: 11901020 | AR96: 0 | AS96: 460955 | AT96: 0 | AU96: 335240 | AV96: 20994405 | AW96: 167620 | AX96: 4232405 | AY96: 125715 | BA96: 2514300 | BB96: 1760010 | BC96: 1005720 | BD96: 628575 | BE96: 1299055
A97: 44776 | B97: 44776.459 | C97: Auction 4. Period CAP3 PL | D97: T3PA | E97: successful | F97: 83.45 | G97: 45 | H97: 87.5 | I97: 81.76 | J97: 82.7 | K97: 1329000 | L97: 4807500 | M97: 67 | N97: 14 | O97: 4.19 | P97: 71754 | Q97: 300469 | R97: 489364 | S97: 166125 | T97: 164714 | U97: 3.62 | V97: 16 | W97: 8 | X97: 110905050 | Y97: PL | AZ97: 110905050
A98: 44775 | B98: 44775.459 | C98: Auction 4. Period CAP3 EU | D98: T3PA | E98: successful | F98: 80.51 | G98: 45 | H98: 82.8 | I98: 79.45 | J98: 80.08 | K98: 1146500 | L98: 3964500 | M98: 76 | N98: 23 | O98: 4 | P98: 52164 | Q98: 208658 | R98: 458141 | S98: 114650 | T98: 157806 | U98: 3.46 | V98: 19 | W98: 10 | X98: 92304715 | Y98: EU | Z98: 1328415 | AA98: 523315 | AB98: 4790345 | AC98: 402550 | AD98: 2375045 | AF98: 281785 | AG98: 1167395 | AH98: 4750090 | AI98: 11593440 | AJ98: 1006375 | AK98: 6601820 | AL98: 603825 | AM98: 1408925 | AN98: 0 | AO98: 11834970 | AP98: 0 | AQ98: 11432420 | AR98: 0 | AS98: 442805 | AT98: 0 | AU98: 322040 | AV98: 20167755 | AW98: 161020 | AX98: 4065755 | AY98: 120765 | BA98: 2415300 | BB98: 1690710 | BC98: 966120 | BD98: 603825 | BE98: 1247905
A99: 44774 | B99: 44774.459 | C99: Auction 4. Period CAP3 EU | D99: T3PA | E99: successful | F99: 79.5 | G99: 45 | H99: 82 | I99: 78.02 | J99: 78.64 | K99: 1146500 | L99: 4318500 | M99: 66 | N99: 11 | O99: 4.13 | P99: 65432 | Q99: 269906 | R99: 500405 | S99: 191083 | T99: 195856 | U99: 3.77 | V99: 16 | W99: 6 | X99: 91146750 | Y99: EU | Z99: 1311750 | AA99: 516750 | AB99: 4730250 | AC99: 397500 | AD99: 2345250 | AF99: 278250 | AG99: 1152750 | AH99: 4690500 | AI99: 11448000 | AJ99: 993750 | AK99: 6519000 | AL99: 596250 | AM99: 1391250 | AN99: 0 | AO99: 11686500 | AP99: 0 | AQ99: 11289000 | AR99: 0 | AS99: 437250 | AT99: 0 | AU99: 318000 | AV99: 19914750 | AW99: 159000 | AX99: 4014750 | AY99: 119250 | BA99: 2385000 | BB99: 1669500 | BC99: 954000 | BD99: 596250 | BE99: 1232250
A100: 44771 | B100: 44771.459 | C100: Auction 4. Period DE | D100: T3PA | E100: successful | F100: 77.96 | G100: 45 | H100: 89.75 | I100: 77.78 | J100: 78.03 | K100: 1944000 | L100: 4570000 | M100: 78 | N100: 41 | O100: 3.9 | P100: 58590 | Q100: 228500 | R100: 448614 | S100: 129600 | T100: 169663 | U100: 2.35 | V100: 20 | W100: 15 | X100: 151554240 | Y100: DE | AE100: 151554240
...
